Workbook

Sheet 00_ReadMe
A1: MGEN Scenario Planning and Business Continuity Stress Test — Auditable Excel Model
A3: Purpose
A4: This workbook is an auditable proposal model aligned to the RFP modules: Module 1 scenario quantification; Module 2 transmission from fuel to SRMC to WESM to margins; Module 3 30/90/180-day liquidity stress; Module 4 trigger-based operating playbook. All hardcoded values are illustrative placeholders for proposal purposes and should be replaced with MGEN data on mobilization.
A8: Model legend | E8: Sheet map
A9: Type | B9: Formatting convention | C9: Example | E9: Sheet | F9: Purpose
A10: Input / assumption | B10: Blue font + yellow fill | C10: Sample | E10: 03_Scenarios | F10: Quantified scenario input matrix (Base, S1, S2, S3)
A11: Formula / calculation | B11: Black font | C11: Sample | E11: 10_FuelLanding | F11: Landed coal, LNG, and oil costs by scenario
A12: Linked from another sheet | B12: Green font | C12: Sample | E12: 12_PlantSRMC | F12: Coal, gas, and oil SRMC build-up
A13: Static constant | B13: Gray fill + gray font | C13: Sample | E13: 13_MeritOrder_WESM | F13: Simplified auditable merit order and WESM price
A14: Deck-ready output | B14: Bold + green fill | C14: Sample | E14: 21_SupplyWholesale_Margin | F14: BCQ / spot / imbalance / repricing sensitivity
A15: Control / mapping note | B15: Purple font + lavender fill | C15: Sample | E15: 31_Retail_EBIT | F15: Segment-level retail EBIT sensitivity
A16: Review / caution note | B16: Orange/italic note box | C16: Sample | E16: 41_Liquidity_Model | F16: 30/90/180-day liquidity stress dashboard logic
A17: Check flag | B17: Red fill / FLAG | C17: Sample | E17: 50_Triggers_Playbook | F17: Trigger thresholds, durations, actions
E18: 60_Outputs | F18: Deck-ready summary tables matching RFP sample structures
E19: 99_Checks | F19: Model integrity checks and tie-outs
A20: Template mapping used in this proposal model: Base = current state, 30-day liquidity horizon uses Scenario 1 (short risk premium), 90-day horizon uses Scenario 2 (sustained elevation), and 180-day horizon uses Scenario 3 (supply disruption). This can be changed easily by relinking 04_HorizonMap.

Sheet 01_Constants
A1: Physical Constants and Conversion Factors
A3: Constant | B3: Value | C3: Unit | D3: Type | E3: Source / Notes
A4: MWh_to_GJ | B4: 3.6 | C4: GJ/MWh | D4: Static | E4: Energy conversion. Source: https://www.eia.gov/energyexplained/units-and-calculators/
A5: MMBtu_to_GJ | B5: 1.055056 | C5: GJ/MMBtu | D5: Static | E5: Energy conversion. Source: https://www.eia.gov/energyexplained/units-and-calculators/
A6: MMBtu_per_bbl_crude_equiv | B6: 5.8 | C6: MMBtu/bbl | D6: Static | E6: Illustrative crude-to-energy conversion. Source: https://www.eia.gov/energyexplained/units-and-calculators/
A7: GJ_per_bbl | B7: =B5*B6 -> 6.1193248 | C7: GJ/bbl | D7: Derived | E7: Uses MMBtu_per_bbl_crude_equiv × MMBtu_to_GJ
A8: kWh_per_MWh | B8: 1000 | C8: kWh/MWh | D8: Static | E8: Electricity conversion
A9: GAR_to_GJ_per_t_factor | B9: 0.0041868 | C9: GJ/t per kcal/kg | D9: Static | E9: Derived conversion factor: GJ/t = kcal/kg × 0.0041868
A10: Coal_CV_GAR5000 | B10: =5000*$B$9 -> 20.934 | C10: GJ/t | D10: Derived | E10: Derived from GAR 5000 kcal/kg benchmark using row 9 conversion factor
A11: Coal_CV_GAR5250 | B11: =5250*$B$9 -> 21.9807 | C11: GJ/t | D11: Derived | E11: Derived from GAR 5250 kcal/kg benchmark using row 9 conversion factor
A12: Coal_CV_GAR5500 | B12: =5500*$B$9 -> 23.0274 | C12: GJ/t | D12: Derived | E12: Derived from GAR 5500 kcal/kg benchmark using row 9 conversion factor

Sheet 02_Inputs_Base
A1: Base Operating Inputs and Generic Proposal Assumptions | H1: Seasonality and Weather Stress Toggles
H2: Industry-assumption placeholders for proposal use; calibrate with historical WESM / Meralco demand and renewable availability data during project.
A3: Input | B3: Value | C3: Unit | D3: Type | E3: Comment | H3: Setting | I3: Value | J3: Unit | K3: Selected | L3: Type | M3: Comment
A4: Oil_product_diff_USD_bbl | B4: 10 | C4: USD/bbl | D4: Input | E4: Illustrative oil product differential used for oil peaker SRMC conversion. | H4: Selected season | I4: Hot-dry | J4: text | K4: =I4 -> Hot-dry | L4: Input | M4: Use Hot-dry / Wet / Cool-dry to stress demand and renewable availability
A5: Coal_dispatch_MWh_month | B5: 700000 | C5: MWh/month | D5: Input | E5: Illustrative monthly coal dispatch volume.
A6: Gas_dispatch_MWh_month | B6: 250000 | C6: MWh/month | D6: Input | E6: Illustrative monthly gas dispatch volume. | H6: Season | I6: Solar mult | J6: Wind mult | K6: Hydro mult | L6: Demand uplift | M6: Comment
A7: Oil_dispatch_MWh_month | B7: 10000 | C7: MWh/month | D7: Input | E7: Illustrative monthly oil peaker dispatch volume. | H7: Hot-dry | I7: 1.02 | J7: 0.95 | K7: 0.85 | L7: 1.05 | M7: Higher temperature load; hydro deration risk
A8: Luzon_demand_MW_toy | B8: 11600 | C8: MW | D8: Input | E8: Representative demand level for simplified merit-order example. | H8: Wet | I8: 0.8 | J8: 1.05 | K8: 1.1 | L8: 1 | M8: Cloud cover suppresses solar; hydro improves
A9: Reserve_volume_MWh_month | B9: 50000 | C9: MW-h/month | D9: Input | E9: Illustrative reserve volume used for reserve revenue sensitivity. | H9: Cool-dry | I9: 0.95 | J9: 1 | K9: 0.95 | L9: 0.97 | M9: Lower cooling demand; more benign conditions
H11: Selected driver | I11: Formula | J11: Unit | K11: Result | L11: Type | M11: Comment
H12: Solar mult | I12: =IF($I$4="Hot-dry",$I$7,IF($I$4="Wet",$I$8,$I$9)) -> 1.02 | J12: x | K12: =I12 -> 1.02 | L12: Formula | M12: Selected season multiplier
H13: Wind mult | I13: =IF($I$4="Hot-dry",$J$7,IF($I$4="Wet",$J$8,$J$9)) -> 0.95 | J13: x | K13: =I13 -> 0.95 | L13: Formula | M13: Selected season multiplier
H14: Hydro mult | I14: =IF($I$4="Hot-dry",$K$7,IF($I$4="Wet",$K$8,$K$9)) -> 0.85 | J14: x | K14: =I14 -> 0.85 | L14: Formula | M14: Selected season multiplier
H15: Demand uplift | I15: =IF($I$4="Hot-dry",$L$7,IF($I$4="Wet",$L$8,$L$9)) -> 1.05 | J15: x | K15: =I15 -> 1.05 | L15: Formula | M15: Selected season multiplier
H16: Luzon Demand Blocks for LWAP Proxy
H17: Block | I17: Base MW | J17: Hours/day | K17: Demand uplift | L17: Final MW | M17: Comment
H18: Off-peak | I18: 8500 | J18: 8 | K18: =$I$15 -> 1.05 | L18: =I18*K18 -> 8925 | M18: Stylized block anchored to Luzon average demand and night trough
H19: Shoulder | I19: 9700 | J19: 10 | K19: =$I$15 -> 1.05 | L19: =I19*K19 -> 10185 | M19: Stylized block representing daytime / evening shoulder
H20: Peak | I20: 11600 | J20: 6 | K20: =$I$15 -> 1.05 | L20: =I20*K20 -> 12180 | M20: Stylized peak block calibrated so base/S1/S2 clear on gas and S3 can move to oil under gas stress
H22: VRE block-shape calibration (base case)
H23: Setting | I23: Off-peak | J23: Shoulder | K23: Peak | L23: Selected-season implied CF | M23: Comment
H24: Solar block shape | I24: 0 | J24: 0.35 | K24: 0.05 | L24: =($J$18*$I$24+$J$19*$J$24+$J$20*$K$24)/24*$I$12 -> 0.1615 | M24: Targets ~16% solar CF in selected season
H25: Wind block shape | I25: 0.34 | J25: 0.31 | K25: 0.29 | L25: =($J$18*$I$25+$J$19*$J$25+$J$20*$K$25)/24*$I$13 -> 0.29925 | M25: Targets ~30% wind CF in selected season
H28: Hydro energy-budget proxy
H29: Setting | I29: Hot-dry | J29: Wet | K29: Cool-dry | L29: Selected | M29: Comment
H30: Hydro_EnergyBudget_GWh_day | I30: 16 | J30: 22 | K30: 18 | L30: =IF($I$4="Hot-dry",$I$30,IF($I$4="Wet",$J$30,$K$30)) -> 16 | M30: Daily hydro energy budget proxy by season
H31: Hydro_PeakMW_Limit | I31: 1200 | J31: 1500 | K31: 1300 | L31: =IF($I$4="Hot-dry",$I$31,IF($I$4="Wet",$J$31,$K$31)) -> 1200 | M31: Seasonal hydro MW cap proxy
H32: RawHydroEnergy_MWh_day | L32: ='11_Plants'!$C$17*'11_Plants'!$D$17*$I$14*('11_Plants'!$E$17*$J$18+'11_Plants'!$F$17*$J$19+'11_Plants'!$G$17*$J$20) -> 23160.543 | M32: Raw hydro energy implied by block profiles before energy-budget scaling
H33: Hydro_BudgetScale | L33: =IF($L$32>0,MIN(1,$L$30*1000/$L$32),1) -> 0.69083008 | M33: Scaling factor applied to hydro block MW so total daily hydro MWh stays within budget
H35: SPC / WESM mitigation controls
H36: togSPC | I36: 0 | J36: 0/1 | K36: Input | L36: Off by default | M36: Toggle to cap block prices under simplified SPC sensitivity
H37: SPC_Cap_PHP_MWh | I37: 9000 | J37: PHP/MWh | K37: Input | L37: Placeholder | M37: Simple cap applied when toggle = 1
H38: SPC_TriggerAvg_PHP_MWh | I38: 9000 | J38: PHP/MWh | K38: Input | L38: Optional placeholder | M38: Reference trigger level for documentation / future refinement

Sheet 03_Scenarios
A1: Module 1 — Quantified Scenario Matrix (RFP-aligned) | I1: Scenario metadata
A2: Scenario framework aligned to proposal slide: S1 = Contained disruption / rapid normalisation; S2 = Sustained regional disruption; S3 = Full-scale regional supply shock. Base column uses pre-escalation market proxy (27 Feb 2026 close) so scenario deltas follow the slide logic. | I2: Data as-of | J2: 46087
I3: Base reference | J3: 2026-02-27 close
I4: Framework source | J4: Proposal Module 1 slide
A6: Variable | B6: Unit | C6: Base | D6: Scenario 1 | E6: Scenario 2 | F6: Scenario 3 | G6: RFP linkage | H6: Notes
A7: Duration_days | B7: days | C7: 0 | D7: 30 | E7: 120 | F7: 180 | G7: Module 1 / p.2, p.5 | H7: Base=pre-escalation proxy; S1/S2/S3 day counts reflect slide language
A8: Brent_USD_bbl | B8: USD/bbl | C8: 72.48 | D8: 80 | E8: 95 | F8: 135 | G8: Brent trajectory | H8: S1 $75–85; S2 $90–100; S3 $120–150+
A9: JKM_USD_MMBtu | B9: USD/MMBtu | C9: 10.725 | D9: 12.33375 | E9: 15.55125 | F9: 23.05875 | G9: JKM trajectory | H9: Central % uplifts vs pre-escalation base
A10: Newcastle_USD_t | B10: USD/t | C10: 115.8 | D10: 124.485 | E10: 141.855 | F10: 167.91 | G10: Newcastle trajectory | H10: Central % uplifts vs pre-escalation base
A11: CoalFreight_USD_t | B11: USD/t | C11: 10 | D11: 11.5 | E11: 14.5 | F11: 19.5 | G11: Freight impact | H11: Central freight uplift vs generic base
A12: CoalInsurance_USD_t | B12: USD/t | C12: 0.5 | D12: 0.75 | E12: 1.25 | F12: 2 | G12: Marine insurance impact | H12: Central insurance / war-risk multiplier proxy
A13: CoalLogisticsAdder_USD_t | B13: USD/t | C13: 0 | D13: 0.5 | E13: 1.5 | F13: 4 | G13: Coal logistics disruption risk | H13: Cost adder for logistics disruption
A14: FX_PHP_USD | B14: PHP/USD | C14: 57.741 | D14: 58.896 | E14: 60.34 | F14: 62.36 | G14: USD/PHP | H14: Central USD strengthening vs pre-escalation base
A15: LNG_Basis_Batangas_USD_MMBtu | B15: USD/MMBtu | C15: 0 | D15: 0.5 | E15: 2 | F15: 5 | G15: DES LNG basis | H15: DES basis vs JKM; full shipping not double counted
A16: LNG_Availability_pct | B16: % | C16: 1 | D16: 0.97 | E16: 0.85 | F16: 0.7 | G16: LNG shipping constraints | H16: Gas availability / throughput multiplier used in merit-order and reserve
A17: CoalDelay_days | B17: days | C17: 0 | D17: 5 | E17: 14 | F17: 28 | G17: Coal logistics disruption risk | H17: Delay days feed liquidity model
A18: BidUplift_pct | B18: % | C18: 0.05 | D18: 0.07 | E18: 0.1 | F18: 0.15 | G18: WESM price formation | H18: Auditable WESM calibration toggle
... A20: BadDebt_mult | B20: x | C20: 1 | D20: 1.05 | E20: 1.15 | F20: 1.3 | G20: Retail credit risk | H20: Retail stress placeholder

Sheet 04_HorizonMap
A1: Horizon Mapping Used for Module 3 Liquidity Stress
A2: To keep the proposal model simple and auditable, 30-day stress uses Scenario 1, 90-day stress uses Scenario 2, and 180-day stress uses Scenario 3. Edit this mapping if the client prefers a different horizon-to-scenario view.
A6: Metric | B6: Base | C6: 30 Days | D6: 90 Days | E6: 180 Days | F6: Comment
A7: Brent_USD_bbl | B7: ='03_Scenarios'!C8 -> 72.48 | C7: ='03_Scenarios'!D8 -> 80 | D7: ='03_Scenarios'!E8 -> 95 | E7: ='03_Scenarios'!F8 -> 135 | F7: Base / S1 / S2 / S3 mapped left to right for liquidity horizons
A8: JKM_USD_MMBtu | B8: ='03_Scenarios'!C9 -> 10.725 | C8: ='03_Scenarios'!D9 -> 12.33375 | D8: ='03_Scenarios'!E9 -> 15.55125 | E8: ='03_Scenarios'!F9 -> 23.05875 | F8: Base / S1 / S2 / S3 mapped left to right for liquidity horizons
A9: Newcastle_USD_t | B9: ='03_Scenarios'!C10 -> 115.8 | C9: ='03_Scenarios'!D10 -> 124.485 | D9: ='03_Scenarios'!E10 -> 141.855 | E9: ='03_Scenarios'!F10 -> 167.91 | F9: Base / S1 / S2 / S3 mapped left to right for liquidity horizons
A10: CoalFreight_USD_t | B10: ='03_Scenarios'!C11 -> 10 | C10: ='03_Scenarios'!D11 -> 11.5 | D10: ='03_Scenarios'!E11 -> 14.5 | E10: ='03_Scenarios'!F11 -> 19.5 | F10: Base / S1 / S2 / S3 mapped left to right for liquidity horizons
A11: CoalInsurance_USD_t | B11: ='03_Scenarios'!C12 -> 0.5 | C11: ='03_Scenarios'!D12 -> 0.75 | D11: ='03_Scenarios'!E12 -> 1.25 | E11: ='03_Scenarios'!F12 -> 2 | F11: Base / S1 / S2 / S3 mapped left to right for liquidity horizons
A12: CoalLogisticsAdder_USD_t | B12: ='03_Scenarios'!C13 -> 0 | C12: ='03_Scenarios'!D13 -> 0.5 | D12: ='03_Scenarios'!E13 -> 1.5 | E12: ='03_Scenarios'!F13 -> 4 | F12: Base / S1 / S2 / S3 mapped left to right for liquidity horizons
A13: FX_PHP_USD | B13: ='03_Scenarios'!C14 -> 57.741 | C13: ='03_Scenarios'!D14 -> 58.896 | D13: ='03_Scenarios'!E14 -> 60.34 | E13: ='03_Scenarios'!F14 -> 62.36 | F13: Base / S1 / S2 / S3 mapped left to right for liquidity horizons
A14: LNG_ShipRegas_USD_MMBtu | B14: ='03_Scenarios'!C15 -> 0 | C14: ='03_Scenarios'!D15 -> 0.5 | D14: ='03_Scenarios'!E15 -> 2 | E14: ='03_Scenarios'!F15 -> 5 | F14: Base / S1 / S2 / S3 mapped left to right for liquidity horizons
A15: GasAvail_pct | B15: ='03_Scenarios'!C16 -> 1 | C15: ='03_Scenarios'!D16 -> 0.97 | D15: ='03_Scenarios'!E16 -> 0.85 | E15: ='03_Scenarios'!F16 -> 0.7 | F15: Base / S1 / S2 / S3 mapped left to right for liquidity horizons
A16: CoalDelay_days | B16: ='03_Scenarios'!C17 -> 0 | C16: ='03_Scenarios'!D17 -> 5 | D16: ='03_Scenarios'!E17 -> 14 | E16: ='03_Scenarios'!F17 -> 28 | F16: Base / S1 / S2 / S3 mapped left to right for liquidity horizons
A17: BidUplift_pct | B17: ='03_Scenarios'!C18 -> 0.05 | C17: ='03_Scenarios'!D18 -> 0.07 | D17: ='03_Scenarios'!E18 -> 0.1 | E17: ='03_Scenarios'!F18 -> 0.15 | F17: Base / S1 / S2 / S3 mapped left to right for liquidity horizons
A18: Reserve_alpha | B18: ='03_Scenarios'!C19 -> 0.25 | C18: ='03_Scenarios'!D19 -> 0.28 | D18: ='03_Scenarios'!E19 -> 0.35 | E18: ='03_Scenarios'!F19 -> 0.45 | F18: Base / S1 / S2 / S3 mapped left to right for liquidity horizons
A19: BadDebt_mult | B19: ='03_Scenarios'!C20 -> 1 | C19: ='03_Scenarios'!D20 -> 1.05 | D19: ='03_Scenarios'!E20 -> 1.15 | E19: ='03_Scenarios'!F20 -> 1.3 | F19: Base / S1 / S2 / S3 mapped left to right for liquidity horizons

Sheet 10_FuelLanding
A1: Fuel Landing Cost Build-up (Module 2 prerequisite)
A2: Green-font rows link directly to scenario inputs; black-font rows are formulas. Coal is now normalized on a GJ basis using the selected GAR/CV case; LNG is split into JKM DES basis, regas/terminal, and delay/demurrage to avoid double counting shipping.
A5: Fuel / Component | B5: Unit | C5: Base | D5: Scenario 1 | E5: Scenario 2 | F5: Scenario 3 | G5: Audit note
A6: Newcastle | B6: USD/t | C6: ='03_Scenarios'!C10 -> 115.8 | D6: ='03_Scenarios'!D10 -> 124.485 | E6: ='03_Scenarios'!E10 -> 141.855 | F6: ='03_Scenarios'!F10 -> 167.91 | G6: Direct scenario pull
A7: Freight | B7: USD/t | C7: ='03_Scenarios'!C11 -> 10 | D7: ='03_Scenarios'!D11 -> 11.5 | E7: ='03_Scenarios'!E11 -> 14.5 | F7: ='03_Scenarios'!F11 -> 19.5 | G7: Direct scenario pull
A8: Insurance | B8: USD/t | C8: ='03_Scenarios'!C12 -> 0.5 | D8: ='03_Scenarios'!D12 -> 0.75 | E8: ='03_Scenarios'!E12 -> 1.25 | F8: ='03_Scenarios'!F12 -> 2 | G8: Direct scenario pull
A9: Logistics adder | B9: USD/t | C9: ='03_Scenarios'!C13 -> 0 | D9: ='03_Scenarios'!D13 -> 0.5 | E9: ='03_Scenarios'!E13 -> 1.5 | F9: ='03_Scenarios'!F13 -> 4 | G9: Direct scenario pull
A10: Coal landed cost | B10: USD/t | C10: =SUM(C6:C9) -> 126.3 | D10: =SUM(D6:D9) -> 137.235 | E10: =SUM(E6:E9) -> 159.105 | F10: =SUM(F6:F9) -> 193.41 | G10: Newcastle + freight + insurance + logistics
A11: FX | B11: PHP/USD | C11: ='03_Scenarios'!C14 -> 57.741 | D11: ='03_Scenarios'!D14 -> 58.896 | E11: ='03_Scenarios'!E14 -> 60.34 | F11: ='03_Scenarios'!F14 -> 62.36 | G11: Direct scenario pull
A12: Coal landed cost | B12: PHP/t | C12: =C10*C11 -> 7292.6883 | D12: =D10*D11 -> 8082.5926 | E12: =E10*E11 -> 9600.3957 | F12: =F10*F11 -> 12061.048 | G12: USD/t × FX
A13: Coal CV (selected) | B13: GJ/t | C13: ='11_Plants'!$F$5 -> 21.9807 | D13: ='11_Plants'!$F$5 -> 21.9807 | E13: ='11_Plants'!$F$5 -> 21.9807 | F13: ='11_Plants'!$F$5 -> 21.9807 | G13: Linked to selected GAR/CV case in 11_Plants
A14: Coal landed cost | B14: PHP/GJ | C14: =C12/C13 -> 331.77689 | D14: =D12/D13 -> 367.71316 | E14: =E12/E13 -> 436.76478 | F14: =F12/F13 -> 548.71081 | G14: (USD/t / selected GJ/t) x FX
A15: LNG / Gas block
A16: JKM | B16: USD/MMBtu | C16: ='03_Scenarios'!C9 -> 10.725 | D16: ='03_Scenarios'!D9 -> 12.33375 | E16: ='03_Scenarios'!E9 -> 15.55125 | F16: ='03_Scenarios'!F9 -> 23.05875
A17: DES basis to Batangas | B17: USD/MMBtu | C17: ='03_Scenarios'!C15 -> 0 | D17: ='03_Scenarios'!D15 -> 0.5 | E17: ='03_Scenarios'!E15 -> 2 | F17: ='03_Scenarios'!F15 -> 5 | G17: Linked to scenario DES basis assumption
A18: Delivered LNG cost | B18: USD/MMBtu | C18: =C16+C17 -> 10.725 | D18: =D16+D17 -> 12.83375 | E18: =E16+E17 -> 17.55125 | F18: =F16+F17 -> 28.05875 | G18: JKM + DES basis
A19: Regas / terminal fee | B19: USD/MMBtu | C19: 0.9 | D19: 1 | E19: 1.1 | F19: 1.3 | G19: Placeholder terminal / regas fee
A20: Delay / demurrage | B20: USD/MMBtu | C20: 0 | D20: 0 | E20: 0.3 | F20: 0.8 | G20: Placeholder disruption / demurrage adder
A21: LNG landed cost | B21: PHP/MMBtu | C21: =(C18+C19+C20)*C11 -> 671.23912 | D21: =(D18+D19+D20)*D11 -> 814.75254 | E21: =(E18+E19+E20)*E11 -> 1143.5184 | F21: =(F18+F19+F20)*F11 -> 1880.6997 | G21: (JKM + basis + regas + delay) x FX
A22: Oil peaker block
A23: Brent | B23: USD/bbl | C23: ='03_Scenarios'!C8 -> 72.48 | D23: ='03_Scenarios'!D8 -> 80 | E23: ='03_Scenarios'!E8 -> 95 | F23: ='03_Scenarios'!F8 -> 135
A24: Product differential | B24: USD/bbl | C24: ='02_Inputs_Base'!$B$4 -> 10 | D24: ='02_Inputs_Base'!$B$4 -> 10 | E24: ='02_Inputs_Base'!$B$4 -> 10 | F24: ='02_Inputs_Base'!$B$4 -> 10
A25: Oil landed cost | B25: USD/bbl | C25: =C23+C24 -> 82.48 | D25: =D23+D24 -> 90 | E25: =E23+E24 -> 105 | F25: =F23+F24 -> 145
A26: Oil landed cost | B26: PHP/bbl | C26: =C25*C11 -> 4762.4777 | D26: =D25*D11 -> 5300.64 | E26: =E25*E11 -> 6335.7 | F26: =F25*F11 -> 9042.2
A27: GJ per bbl | B27: GJ/bbl | C27: ='01_Constants'!$B$6 -> 5.8 | D27: ='01_Constants'!$B$6 -> 5.8 | E27: ='01_Constants'!$B$6 -> 5.8 | F27: ='01_Constants'!$B$6 -> 5.8
A28: Oil fuel cost | B28: PHP/GJ | C28: =C26/C27 -> 821.11684 | D28: =D26/D27 -> 913.90345 | E28: =E26/E27 -> 1092.3621 | F28: =F26/F27 -> 1559

Sheet 11_Plants
A1: Plant Cluster Assumptions (Generic placeholders; replace with MGEN input)
A3: Cluster | B3: Fuel | C3: Capacity (MW) | D3: Base availability % | E3: Heat rate (GJ/MWh) | F3: Coal CV (GJ/t) | G3: Variable O&M (PHP/MWh) | H3: Base dispatch (MWh/month) | I3: Comment | J3: Coal GAR case | K3: Selected CV (GJ/t)
A5: Coal cluster | B5: Coal | C5: 1200 | D5: 0.9 | E5: 9.6 | F5: =$K$5 -> 21.9807 | G5: 260 | H5: 700000 | I5: Generic HELE coal cluster placeholder | J5: GAR 5250 | K5: =IF($J$5="GAR 5000",'01_Constants'!$B$10,IF($J$5="GAR 5500",'01_Constants'!$B$12,'01_Constants'!$B$11)) -> 21.9807
A6: Gas cluster | B6: Gas / LNG | C6: 1200 | D6: 0.88 | E6: 7.2 | G6: 180 | H6: 250000 | I6: Generic CCGT / LNG cluster placeholder
A7: Oil peakers | B7: Oil | C7: 300 | D7: 0.95 | E7: 11.5 | G7: 450 | H7: 10000 | I7: Illustrative oil peaker cluster
A10: Luzon WESM stack inputs (system-level; auditable proxy)
A11: Dependable capacities use public DOE Luzon 2024 data; availability and profile factors are generic placeholders for proposal use and must be refined with historical IEMOP / client calibration.
A12: Cluster | B12: Source basis | C12: Dependable MW | D12: Base tech avail % | E12: Offpeak profile | F12: Shoulder profile | G12: Peak profile | H12: Seasonal/weather driver | I12: Scenario factor | J12: Comment | K12: Cluster type
A13: Solar | B13: DOE 2024 dependable | C13: 1674 | D13: 0.98 | E13: ='02_Inputs_Base'!$I$24 -> 0 | F13: ='02_Inputs_Base'!$J$24 -> 0.35 | G13: ='02_Inputs_Base'!$K$24 -> 0.05 | H13: Solar mult | I13: 1.0x | J13: Daylight-driven profile | K13: Variable RE
A14: Wind | B14: DOE 2024 dependable | C14: 337 | D14: 0.95 | E14: ='02_Inputs_Base'!$I$25 -> 0.34 | F14: ='02_Inputs_Base'!$J$25 -> 0.31 | G14: ='02_Inputs_Base'!$K$25 -> 0.29 | H14: Wind mult | I14: 1.0x | J14: Variable RE | K14: Variable RE
A15: Geothermal | B15: DOE 2024 dependable | C15: 714 | D15: 0.92 | E15: 1 | F15: 1 | G15: 1 | H15: None | I15: 1.0x | J15: Baseload renewable | K15: Must-run low SRMC
A16: Biomass | B16: DOE 2024 dependable | C16: 145 | D16: 0.85 | E16: 1 | F16: 1 | G16: 1 | H16: None | I16: 1.0x | J16: Stable renewable / thermal | K16: Low-mid SRMC
A17: Hydro | B17: DOE 2024 dependable | C17: 2382 | D17: 0.93 | E17: 0.6 | F17: 0.45 | G17: 0.5 | H17: Hydro mult | I17: 1.0x | J17: Peaking/flex resource | K17: Opportunity-cost peaking
A18: Coal | B18: DOE 2024 dependable | C18: 8589 | D18: 0.92 | E18: 1 | F18: 1 | G18: 1 | H18: None | I18: 1.0x | J18: Backbone baseload | K18: Thermal
A19: Gas | B19: DOE 2024 dependable | C19: 3281 | D19: 0.88 | E19: 1 | F19: 1 | G19: 1 | H19: None | I19: LNG_Availability_pct | J19: Fuel-constrained thermal; derated by LNG availability assumption | K19: Thermal
A20: Oil | B20: DOE 2024 dependable | C20: 1648 | D20: 0.95 | E20: 1 | F20: 1 | G20: 1 | H20: None | I20: 1.0x | J20: Peaker / scarcity resource | K20: Thermal
A21: ESS | B21: DOE 2024 dependable | C21: 341 | D21: 0.95 | E21: 0.05 | F21: 0.1 | G21: 0.25 | H21: None | I21: 1.0x | J21: Short-duration flexibility | K21: Flex

Sheet 12_PlantSRMC
A1: Plant SRMC Build-up by Scenario
A2: This sheet is the auditable core of Module 2A. Coal now uses a GJ-normalized landed cost tied to the selected GAR/CV case; LNG now uses DES basis + regas + delay split before converting to PHP/MMBtu.
A5: Metric | B5: Unit | C5: Base | D5: Scenario 1 | E5: Scenario 2 | F5: Scenario 3 | G5: Formula note
A6: Coal heat rate | B6: GJ/MWh | C6: ='11_Plants'!$E$5 -> 9.6 | D6: ='11_Plants'!$E$5 -> 9.6 | E6: ='11_Plants'!$E$5 -> 9.6 | F6: ='11_Plants'!$E$5 -> 9.6
A7: Coal CV | B7: GJ/t | C7: ='11_Plants'!$F$5 -> 21.9807 | D7: ='11_Plants'!$F$5 -> 21.9807 | E7: ='11_Plants'!$F$5 -> 21.9807 | F7: ='11_Plants'!$F$5 -> 21.9807
A8: Coal landed cost | B8: PHP/GJ | C8: ='10_FuelLanding'!C14 -> 331.77689 | D8: ='10_FuelLanding'!D14 -> 367.71316 | E8: ='10_FuelLanding'!E14 -> 436.76478 | F8: ='10_FuelLanding'!F14 -> 548.71081
A9: Coal fuel cost | B9: PHP/MWh | C9: =C6*C8 -> 3185.0582 | D9: =D6*D8 -> 3530.0463 | E9: =E6*E8 -> 4192.9419 | F9: =F6*F8 -> 5267.6237
A10: Coal variable O&M | B10: PHP/MWh | C10: ='11_Plants'!$G$5 -> 260 | D10: ='11_Plants'!$G$5 -> 260 | E10: ='11_Plants'!$G$5 -> 260 | F10: ='11_Plants'!$G$5 -> 260
A11: Coal landed cost | B11: PHP/t | C11: ='10_FuelLanding'!C12 -> 7292.6883 | D11: ='10_FuelLanding'!D12 -> 8082.5926 | E11: ='10_FuelLanding'!E12 -> 9600.3957 | F11: ='10_FuelLanding'!F12 -> 12061.048
A12: Coal SRMC | B12: PHP/MWh | C12: =C9+C10 -> 3445.0582 | D12: =D9+D10 -> 3790.0463 | E12: =E9+E10 -> 4452.9419 | F12: =F9+F10 -> 5527.6237 | G12: Coal fuel + VOM using GAR/CV-normalized landed cost
A15: Gas heat rate | B15: GJ/MWh | C15: ='11_Plants'!$E$6 -> 7.2 | D15: ='11_Plants'!$E$6 -> 7.2 | E15: ='11_Plants'!$E$6 -> 7.2 | F15: ='11_Plants'!$E$6 -> 7.2
A16: GJ per MMBtu | B16: GJ/MMBtu | C16: ='01_Constants'!$B$5 -> 1.055056 | D16: ='01_Constants'!$B$5 -> 1.055056 | E16: ='01_Constants'!$B$5 -> 1.055056 | F16: ='01_Constants'!$B$5 -> 1.055056
A17: Gas heat rate | B17: MMBtu/MWh | C17: =C15/C16 -> 6.8242823 | D17: =D15/D16 -> 6.8242823 | E17: =E15/E16 -> 6.8242823 | F17: =F15/F16 -> 6.8242823
A18: LNG landed cost | B18: PHP/MMBtu | C18: ='10_FuelLanding'!C21 -> 671.23912 | D18: ='10_FuelLanding'!D21 -> 814.75254 | E18: ='10_FuelLanding'!E21 -> 1143.5184 | F18: ='10_FuelLanding'!F21 -> 1880.6997
A19: Gas fuel cost | B19: PHP/MWh | C19: =C17*C18 -> 4580.7253 | D19: =D17*D18 -> 5560.1013 | E19: =E17*E18 -> 7803.6926 | F19: =F17*F18 -> 12834.425
A20: Gas variable O&M | B20: PHP/MWh | C20: ='11_Plants'!$G$6 -> 180 | D20: ='11_Plants'!$G$6 -> 180 | E20: ='11_Plants'!$G$6 -> 180 | F20: ='11_Plants'!$G$6 -> 180
A21: Gas SRMC | B21: PHP/MWh | C21: =C19+C20 -> 4760.7253 | D21: =D19+D20 -> 5740.1013 | E21: =E19+E20 -> 7983.6926 | F21: =F19+F20 -> 13014.425 | G21: Gas fuel + VOM
A24: Oil heat rate | B24: GJ/MWh | C24: ='11_Plants'!$E$7 -> 11.5 | D24: ='11_Plants'!$E$7 -> 11.5 | E24: ='11_Plants'!$E$7 -> 11.5 | F24: ='11_Plants'!$E$7 -> 11.5
A25: Oil fuel cost | B25: PHP/GJ | C25: ='10_FuelLanding'!C28 -> 821.11684 | D25: ='10_FuelLanding'!D28 -> 913.90345 | E25: ='10_FuelLanding'!E28 -> 1092.3621 | F25: ='10_FuelLanding'!F28 -> 1559
A26: Oil fuel cost | B26: PHP/MWh | C26: =C24*C25 -> 9442.8437 | D26: =D24*D25 -> 10509.89 | E26: =E24*E25 -> 12562.164 | F26: =F24*F25 -> 17928.5
A27: Oil variable O&M | B27: PHP/MWh | C27: ='11_Plants'!$G$7 -> 450 | D27: ='11_Plants'!$G$7 -> 450 | E27: ='11_Plants'!$G$7 -> 450 | F27: ='11_Plants'!$G$7 -> 450
A28: Oil SRMC | B28: PHP/MWh | C28: =C26+C27 -> 9892.8437 | D28: =D26+D27 -> 10959.89 | E28: =E26+E27 -> 13012.164 | F28: =F26+F27 -> 18378.5 | G28: Oil fuel + VOM
A31: Coal dispatch | B31: MWh/month | C31: ='11_Plants'!$H$5 -> 700000 | D31: ='11_Plants'!$H$5 -> 700000 | E31: ='11_Plants'!$H$5 -> 700000 | F31: ='11_Plants'!$H$5 -> 700000
A32: Gas dispatch | B32: MWh/month | C32: ='11_Plants'!$H$6*'03_Scenarios'!C16 -> 250000 | D32: ='11_Plants'!$H$6*'03_Scenarios'!D16 -> 242500 | E32: ='11_Plants'!$H$6*'03_Scenarios'!E16 -> 212500 | F32: ='11_Plants'!$H$6*'03_Scenarios'!F16 -> 175000
A33: Oil dispatch | B33: MWh/month | C33: ='11_Plants'!$H$7+('11_Plants'!$H$6-C32) -> 10000 | D33: ='11_Plants'!$H$7+('11_Plants'!$H$6-D32) -> 17500 | E33: ='11_Plants'!$H$7+('11_Plants'!$H$6-E32) -> 47500 | F33: ='11_Plants'!$H$7+('11_Plants'!$H$6-F32) -> 85000
A34: Total dispatch | B34: MWh/month | C34: =SUM(C31:C33) -> 960000 | D34: =SUM(D31:D33) -> 960000 | E34: =SUM(E31:E33) -> 960000 | F34: =SUM(F31:F33) -> 960000
A35: Weighted fleet SRMC | B35: PHP/MWh | C35: =(C12*C31+C21*C32+C28*C33)/C34 -> 3854.8442 | D35: =(D12*D31+D21*D32+D28*D33)/D34 -> 4413.3386 | E35: =(E12*E31+E21*E32+E28*E33)/E34 -> 5657.9915 | F35: =(F12*F31+F21*F32+F28*F33)/F34 -> 8030.2433 | G35: Dispatch-weighted portfolio SRMC
A38: Luzon market stack SRMC anchors (proxy values for merit-order model)
A39: Low-SRMC technologies use generic placeholder anchor values; coal/gas/oil rows link to the auditable plant SRMC build-up above.
A40: Cluster | B40: Unit | C40: Base | D40: Scenario 1 | E40: Scenario 2 | F40: Scenario 3 | G40: Comment
A41: Solar | B41: PHP/MWh | C41: 0 | D41: 0 | E41: 0 | F41: 0 | G41: Near-zero marginal cost placeholder
A42: Wind | B42: PHP/MWh | C42: 0 | D42: 0 | E42: 0 | F42: 0 | G42: Near-zero marginal cost placeholder
A43: Geothermal | B43: PHP/MWh | C43: 600 | D43: 650 | E43: 700 | F43: 800 | G43: Generic low SRMC renewable placeholder
A44: Biomass | B44: PHP/MWh | C44: 1200 | D44: 1250 | E44: 1300 | F44: 1400 | G44: Generic biomass SRMC placeholder
A45: Hydro | B45: PHP/MWh | C45: 1500 | D45: 1600 | E45: 1900 | F45: 2300 | G45: Opportunity-cost hydro proxy; higher under scarcity
A46: ESS | B46: PHP/MWh | C46: 3000 | D46: 3200 | E46: 3500 | F46: 4200 | G46: Storage discharge opportunity-cost proxy
A47: Coal | B47: PHP/MWh | C47: =C12 -> 3445.0582 | D47: =D12 -> 3790.0463 | E47: =E12 -> 4452.9419 | F47: =F12 -> 5527.6237 | G47: Linked to detailed coal SRMC
A48: Gas | B48: PHP/MWh | C48: =C21 -> 4760.7253 | D48: =D21 -> 5740.1013 | E48: =E21 -> 7983.6926 | F48: =F21 -> 13014.425 | G48: Linked to detailed gas SRMC
A49: Oil | B49: PHP/MWh | C49: =C28 -> 9892.8437 | D49: =D28 -> 10959.89 | E49: =E28 -> 13012.164 | F49: =F28 -> 18378.5 | G49: Linked to detailed oil SRMC

Sheet 13_MeritOrder_WESM
A1: Luzon WESM merit-order proxy (realistic technology stack)
A2: Off-peak / shoulder / peak demand blocks and DOE-based technology clusters replace the original toy 3-unit stack. LNG_Availability_pct derates gas MW directly; prices are auditable merit-order proxies, not nodal dispatch replication.
A5: Metric | B5: Unit | C5: Base | D5: Scenario 1 | E5: Scenario 2 | F5: Scenario 3 | G5: Audit note | M5: Base idx | N5: S1 idx | O5: S2 idx | P5: S3 idx
A6: Off-peak demand | B6: MW | C6: ='02_Inputs_Base'!$L$18 -> 8925 | D6: ='02_Inputs_Base'!$L$18 -> 8925 | E6: ='02_Inputs_Base'!$L$18 -> 8925 | F6: ='02_Inputs_Base'!$L$18 -> 8925 | G6: Demand blocks from 02_Inputs_Base seasonal toggle | M6: =IF(H32<C6,9,1+IF(H24<C6,1,0)+IF(H25<C6,1,0)+IF(H26<C6,1,0)+IF(H27<C6,1,0)+IF(H28<C6,1,0)+IF(H29<C6,1,0)+IF(H30<C6,1,0)+IF(H31<C6,1,0)) -> 7 | N6: =IF(H45<D6,9,1+IF(H37<D6,1,0)+IF(H38<D6,1,0)+IF(H39<D6,1,0)+IF(H40<D6,1,0)+IF(H41<D6,1,0)+IF(H42<D6,1,0)+IF(H43<D6,1,0)+IF(H44<D6,1,0)) -> 7 | O6: =IF(H58<E6,9,1+IF(H50<E6,1,0)+IF(H51<E6,1,0)+IF(H52<E6,1,0)+IF(H53<E6,1,0)+IF(H54<E6,1,0)+IF(H55<E6,1,0)+IF(H56<E6,1,0)+IF(H57<E6,1,0)) -> 7 | P6: =IF(H71<F6,9,1+IF(H63<F6,1,0)+IF(H64<F6,1,0)+IF(H65<F6,1,0)+IF(H66<F6,1,0)+IF(H67<F6,1,0)+IF(H68<F6,1,0)+IF(H69<F6,1,0)+IF(H70<F6,1,0)) -> 7
A7: Shoulder demand | B7: MW | C7: ='02_Inputs_Base'!$L$19 -> 10185 | D7: ='02_Inputs_Base'!$L$19 -> 10185 | E7: ='02_Inputs_Base'!$L$19 -> 10185 | F7: ='02_Inputs_Base'!$L$19 -> 10185 | M7: =IF(I32<C7,9,1+IF(I24<C7,1,0)+IF(I25<C7,1,0)+IF(I26<C7,1,0)+IF(I27<C7,1,0)+IF(I28<C7,1,0)+IF(I29<C7,1,0)+IF(I30<C7,1,0)+IF(I31<C7,1,0)) -> 8 | N7: =IF(I45<D7,9,1+IF(I37<D7,1,0)+IF(I38<D7,1,0)+IF(I39<D7,1,0)+IF(I40<D7,1,0)+IF(I41<D7,1,0)+IF(I42<D7,1,0)+IF(I43<D7,1,0)+IF(I44<D7,1,0)) -> 8 | O7: =IF(I58<E7,9,1+IF(I50<E7,1,0)+IF(I51<E7,1,0)+IF(I52<E7,1,0)+IF(I53<E7,1,0)+IF(I54<E7,1,0)+IF(I55<E7,1,0)+IF(I56<E7,1,0)+IF(I57<E7,1,0)) -> 8 | P7: =IF(I71<F7,9,1+IF(I63<F7,1,0)+IF(I64<F7,1,0)+IF(I65<F7,1,0)+IF(I66<F7,1,0)+IF(I67<F7,1,0)+IF(I68<F7,1,0)+IF(I69<F7,1,0)+IF(I70<F7,1,0)) -> 8
A8: Peak demand | B8: MW | C8: ='02_Inputs_Base'!$L$20 -> 12180 | D8: ='02_Inputs_Base'!$L$20 -> 12180 | E8: ='02_Inputs_Base'!$L$20 -> 12180 | F8: ='02_Inputs_Base'!$L$20 -> 12180 | M8: =IF(J32<C8,9,1+IF(J24<C8,1,0)+IF(J25<C8,1,0)+IF(J26<C8,1,0)+IF(J27<C8,1,0)+IF(J28<C8,1,0)+IF(J29<C8,1,0)+IF(J30<C8,1,0)+IF(J31<C8,1,0)) -> 8 | N8: =IF(J45<D8,9,1+IF(J37<D8,1,0)+IF(J38<D8,1,0)+IF(J39<D8,1,0)+IF(J40<D8,1,0)+IF(J41<D8,1,0)+IF(J42<D8,1,0)+IF(J43<D8,1,0)+IF(J44<D8,1,0)) -> 8 | O8: =IF(J58<E8,9,1+IF(J50<E8,1,0)+IF(J51<E8,1,0)+IF(J52<E8,1,0)+IF(J53<E8,1,0)+IF(J54<E8,1,0)+IF(J55<E8,1,0)+IF(J56<E8,1,0)+IF(J57<E8,1,0)) -> 9 | P8: =IF(J71<F8,9,1+IF(J63<F8,1,0)+IF(J64<F8,1,0)+IF(J65<F8,1,0)+IF(J66<F8,1,0)+IF(J67<F8,1,0)+IF(J68<F8,1,0)+IF(J69<F8,1,0)+IF(J70<F8,1,0)) -> 9
A9: Off-peak marginal cluster | B9: text | C9: =CHOOSE(M6,"Solar","Wind","Geothermal","Biomass","Hydro","ESS","Coal","Gas","Oil") -> Coal | D9: =CHOOSE(N6,"Solar","Wind","Geothermal","Biomass","Hydro","ESS","Coal","Gas","Oil") -> Coal | E9: =CHOOSE(O6,"Solar","Wind","Geothermal","Biomass","Hydro","ESS","Coal","Gas","Oil") -> Coal | F9: =CHOOSE(P6,"Solar","Wind","Geothermal","Biomass","Hydro","ESS","Coal","Gas","Oil") -> Coal | G9: Marginal technology by block
A10: Shoulder marginal cluster | B10: text | C10: =CHOOSE(M7,"Solar","Wind","Geothermal","Biomass","Hydro","ESS","Coal","Gas","Oil") -> Gas | D10: =CHOOSE(N7,"Solar","Wind","Geothermal","Biomass","Hydro","ESS","Coal","Gas","Oil") -> Gas | E10: =CHOOSE(O7,"Solar","Wind","Geothermal","Biomass","Hydro","ESS","Coal","Gas","Oil") -> Gas | F10: =CHOOSE(P7,"Solar","Wind","Geothermal","Biomass","Hydro","ESS","Coal","Gas","Oil") -> Gas
A11: Peak marginal cluster | B11: text | C11: =CHOOSE(M8,"Solar","Wind","Geothermal","Biomass","Hydro","ESS","Coal","Gas","Oil") -> Gas | D11: =CHOOSE(N8,"Solar","Wind","Geothermal","Biomass","Hydro","ESS","Coal","Gas","Oil") -> Gas | E11: =CHOOSE(O8,"Solar","Wind","Geothermal","Biomass","Hydro","ESS","Coal","Gas","Oil") -> Oil | F11: =CHOOSE(P8,"Solar","Wind","Geothermal","Biomass","Hydro","ESS","Coal","Gas","Oil") -> Oil
A12: Off-peak clearing price | B12: PHP/MWh | C12: =IF('02_Inputs_Base'!$I$36=1,MIN(CHOOSE(M6,G24,G25,G26,G27,G28,G29,G30,G31,G32),'02_Inputs_Base'!$I$37),CHOOSE(M6,G24,G25,G26,G27,G28,G29,G30,G31,G32)) -> 3445.0582 | D12: =IF('02_Inputs_Base'!$I$36=1,MIN(CHOOSE(N6,G37,G38,G39,G40,G41,G42,G43,G44,G45),'02_Inputs_Base'!$I$37),CHOOSE(N6,G37,G38,G39,G40,G41,G42,G43,G44,G45)) -> 3790.0463 | E12: =IF('02_Inputs_Base'!$I$36=1,MIN(CHOOSE(O6,G50,G51,G52,G53,G54,G55,G56,G57,G58),'02_Inputs_Base'!$I$37),CHOOSE(O6,G50,G51,G52,G53,G54,G55,G56,G57,G58)) -> 4452.9419 | F12: =IF('02_Inputs_Base'!$I$36=1,MIN(CHOOSE(P6,G63,G64,G65,G66,G67,G68,G69,G70,G71),'02_Inputs_Base'!$I$37),CHOOSE(P6,G63,G64,G65,G66,G67,G68,G69,G70,G71)) -> 5527.6237 | G12: Clearing price = marginal cluster SRMC
A13: Shoulder clearing price | B13: PHP/MWh | C13: =IF('02_Inputs_Base'!$I$36=1,MIN(CHOOSE(M7,G24,G25,G26,G27,G28,G29,G30,G31,G32),'02_Inputs_Base'!$I$37),CHOOSE(M7,G24,G25,G26,G27,G28,G29,G30,G31,G32)) -> 4760.7253 | D13: =IF('02_Inputs_Base'!$I$36=1,MIN(CHOOSE(N7,G37,G38,G39,G40,G41,G42,G43,G44,G45),'02_Inputs_Base'!$I$37),CHOOSE(N7,G37,G38,G39,G40,G41,G42,G43,G44,G45)) -> 5740.1013 | E13: =IF('02_Inputs_Base'!$I$36=1,MIN(CHOOSE(O7,G50,G51,G52,G53,G54,G55,G56,G57,G58),'02_Inputs_Base'!$I$37),CHOOSE(O7,G50,G51,G52,G53,G54,G55,G56,G57,G58)) -> 7983.6926 | F13: =IF('02_Inputs_Base'!$I$36=1,MIN(CHOOSE(P7,G63,G64,G65,G66,G67,G68,G69,G70,G71),'02_Inputs_Base'!$I$37),CHOOSE(P7,G63,G64,G65,G66,G67,G68,G69,G70,G71)) -> 13014.425
A14: Peak clearing price | B14: PHP/MWh | C14: =IF('02_Inputs_Base'!$I$36=1,MIN(CHOOSE(M8,G24,G25,G26,G27,G28,G29,G30,G31,G32),'02_Inputs_Base'!$I$37),CHOOSE(M8,G24,G25,G26,G27,G28,G29,G30,G31,G32)) -> 4760.7253 | D14: =IF('02_Inputs_Base'!$I$36=1,MIN(CHOOSE(N8,G37,G38,G39,G40,G41,G42,G43,G44,G45),'02_Inputs_Base'!$I$37),CHOOSE(N8,G37,G38,G39,G40,G41,G42,G43,G44,G45)) -> 5740.1013 | E14: =IF('02_Inputs_Base'!$I$36=1,MIN(CHOOSE(O8,G50,G51,G52,G53,G54,G55,G56,G57,G58),'02_Inputs_Base'!$I$37),CHOOSE(O8,G50,G51,G52,G53,G54,G55,G56,G57,G58)) -> 13012.164 | F14: =IF('02_Inputs_Base'!$I$36=1,MIN(CHOOSE(P8,G63,G64,G65,G66,G67,G68,G69,G70,G71),'02_Inputs_Base'!$I$37),CHOOSE(P8,G63,G64,G65,G66,G67,G68,G69,G70,G71)) -> 18378.5
A15: Weighted price pre-uplift | B15: PHP/MWh | C15: =(C12*'02_Inputs_Base'!$J$18+C13*'02_Inputs_Base'!$J$19+C14*'02_Inputs_Base'!$J$20)/24 -> 4322.1696 | D15: =(D12*'02_Inputs_Base'!$J$18+D13*'02_Inputs_Base'!$J$19+D14*'02_Inputs_Base'!$J$20)/24 -> 5090.083 | E15: =(E12*'02_Inputs_Base'!$J$18+E13*'02_Inputs_Base'!$J$19+E14*'02_Inputs_Base'!$J$20)/24 -> 8063.8935 | F15: =(F12*'02_Inputs_Base'!$J$18+F13*'02_Inputs_Base'!$J$19+F14*'02_Inputs_Base'!$J$20)/24 -> 11859.843 | G15: Hours/day weighted average pre-uplift
A16: WESM Avg Luzon | B16: PHP/MWh | C16: =C15*(1+'03_Scenarios'!$C$18) -> 4538.2781 | D16: =D15*(1+'03_Scenarios'!$D$18) -> 5446.3888 | E16: =E15*(1+'03_Scenarios'!$E$18) -> 8870.2828 | F16: =F15*(1+'03_Scenarios'!$F$18) -> 13638.82 | G16: LWAP proxy = weighted price × (1+bid uplift)
A17: Peak adequacy buffer | B17: MW | C17: =J32-C8 -> 1858.1518 | D17: =J45-D8 -> 1771.5334 | E17: =J58-E8 -> 1425.0598 | F17: =J71-F8 -> 991.96785 | G17: Peak available supply minus peak demand
A18: Peak scarcity ratio | B18: x | C18: =IF(J32>0,C8/J32,0) -> 0.86763558 | D18: =IF(J45>0,D8/J45,0) -> 0.87302231 | E18: =IF(J58>0,E8/J58,0) -> 0.89525516 | F18: =IF(J71>0,F8/J71,0) -> 0.92469099 | G18: Peak demand / peak available supply
A19: Merit-order check | B19: flag | C19: =IF(AND('12_PlantSRMC'!C12<='12_PlantSRMC'!C21,'12_PlantSRMC'!C21<='12_PlantSRMC'!C28),"OK","FLAG") -> OK | D19: =IF(AND('12_PlantSRMC'!D12<='12_PlantSRMC'!D21,'12_PlantSRMC'!D21<='12_PlantSRMC'!D28),"OK","FLAG") -> OK | E19: =IF(AND('12_PlantSRMC'!E12<='12_PlantSRMC'!E21,'12_PlantSRMC'!E21<='12_PlantSRMC'!E28),"OK","FLAG") -> OK | F19: =IF(AND('12_PlantSRMC'!F12<='12_PlantSRMC'!F21,'12_PlantSRMC'!F21<='12_PlantSRMC'!F28),"OK","FLAG") -> OK | G19: Checks coal <= gas <= oil SRMC
A22: Base stack audit
A23: Cluster | B23: Cap MW | C23: Tech avail | D23: Off-peak MW | E23: Shoulder MW | F23: Peak MW | G23: SRMC | H23: Cum off | I23: Cum shoulder | J23: Cum peak | K23: Note
A24: Solar | B24: ='11_Plants'!$C$13 -> 1674 | C24: ='11_Plants'!$D$13 -> 0.98 | D24: =B24*C24*'11_Plants'!$E$13*'02_Inputs_Base'!$I$12*1 -> 0 | E24: =B24*C24*'11_Plants'!$F$13*'02_Inputs_Base'!$I$12*1 -> 585.66564 | F24: =B24*C24*'11_Plants'!$G$13*'02_Inputs_Base'!$I$12*1 -> 83.66652 | G24: ='12_PlantSRMC'!$C$41 -> 0 | H24: =D24 -> 0 | I24: =E24 -> 585.66564 | J24: =F24 -> 83.66652 | K24: ='11_Plants'!$J$13 -> Daylight-driven profile
A25: Wind | B25: ='11_Plants'!$C$14 -> 337 | C25: ='11_Plants'!$D$14 -> 0.95 | D25: =B25*C25*'11_Plants'!$E$14*'02_Inputs_Base'!$I$13*1 -> 103.40845 | E25: =B25*C25*'11_Plants'!$F$14*'02_Inputs_Base'!$I$13*1 -> 94.284175 | F25: =B25*C25*'11_Plants'!$G$14*'02_Inputs_Base'!$I$13*1 -> 88.201325 | G25: ='12_PlantSRMC'!$C$42 -> 0 | H25: =H24+D25 -> 103.40845 | I25: =I24+E25 -> 679.94981 | J25: =J24+F25 -> 171.86784 | K25: ='11_Plants'!$J$14 -> Variable RE
A26: Geothermal | B26: ='11_Plants'!$C$15 -> 714 | C26: ='11_Plants'!$D$15 -> 0.92 | D26: =B26*C26*'11_Plants'!$E$15*1*1 -> 656.88 | E26: =B26*C26*'11_Plants'!$F$15*1*1 -> 656.88 | F26: =B26*C26*'11_Plants'!$G$15*1*1 -> 656.88 | G26: ='12_PlantSRMC'!$C$43 -> 600 | H26: =H25+D26 -> 760.28845 | I26: =I25+E26 -> 1336.8298 | J26: =J25+F26 -> 828.74784 | K26: ='11_Plants'!$J$15 -> Baseload renewable
A27: Biomass | B27: ='11_Plants'!$C$16 -> 145 | C27: ='11_Plants'!$D$16 -> 0.85 | D27: =B27*C27*'11_Plants'!$E$16*1*1 -> 123.25 | E27: =B27*C27*'11_Plants'!$F$16*1*1 -> 123.25 | F27: =B27*C27*'11_Plants'!$G$16*1*1 -> 123.25 | G27: ='12_PlantSRMC'!$C$44 -> 1200 | H27: =H26+D27 -> 883.53845 | I27: =I26+E27 -> 1460.0798 | J27: =J26+F27 -> 951.99784 | K27: ='11_Plants'!$J$16 -> Stable renewable / thermal
A28: Hydro | B28: ='11_Plants'!$C$17 -> 2382 | C28: ='11_Plants'!$D$17 -> 0.93 | D28: =MIN(B28*C28*'11_Plants'!$E$17*'02_Inputs_Base'!$I$14*'02_Inputs_Base'!$L$33,'02_Inputs_Base'!$L$31) -> 780.4878 | E28: =MIN(B28*C28*'11_Plants'!$F$17*'02_Inputs_Base'!$I$14*'02_Inputs_Base'!$L$33,'02_Inputs_Base'!$L$31) -> 585.36585 | F28: =MIN(B28*C28*'11_Plants'!$G$17*'02_Inputs_Base'!$I$14*'02_Inputs_Base'!$L$33,'02_Inputs_Base'!$L$31) -> 650.4065 | G28: ='12_PlantSRMC'!$C$45 -> 1500 | H28: =H27+D28 -> 1664.0263 | I28: =I27+E28 -> 2045.4457 | J28: =J27+F28 -> 1602.4043 | K28: ='11_Plants'!$J$17 -> Peaking/flex resource
A29: ESS | B29: ='11_Plants'!$C$21 -> 341 | C29: ='11_Plants'!$D$21 -> 0.95 | D29: =B29*C29*'11_Plants'!$E$21*1*1 -> 16.1975 | E29: =B29*C29*'11_Plants'!$F$21*1*1 -> 32.395 | F29: =B29*C29*'11_Plants'!$G$21*1*1 -> 80.9875 | G29: ='12_PlantSRMC'!$C$46 -> 3000 | H29: =H28+D29 -> 1680.2238 | I29: =I28+E29 -> 2077.8407 | J29: =J28+F29 -> 1683.3918 | K29: ='11_Plants'!$J$21 -> Short-duration flexibility
A30: Coal | B30: ='11_Plants'!$C$18 -> 8589 | C30: ='11_Plants'!$D$18 -> 0.92 | D30: =B30*C30*'11_Plants'!$E$18*1*1 -> 7901.88 | E30: =B30*C30*'11_Plants'!$F$18*1*1 -> 7901.88 | F30: =B30*C30*'11_Plants'!$G$18*1*1 -> 7901.88 | G30: ='12_PlantSRMC'!$C$47 -> 3445.0582 | H30: =H29+D30 -> 9582.1038 | I30: =I29+E30 -> 9979.7207 | J30: =J29+F30 -> 9585.2718 | K30: ='11_Plants'!$J$18 -> Backbone baseload
A31: Gas | B31: ='11_Plants'!$C$19 -> 3281 | C31: ='11_Plants'!$D$19 -> 0.88 | D31: =B31*C31*'11_Plants'!$E$19*1*'03_Scenarios'!$C16 -> 2887.28 | E31: =B31*C31*'11_Plants'!$F$19*1*'03_Scenarios'!$C16 -> 2887.28 | F31: =B31*C31*'11_Plants'!$G$19*1*'03_Scenarios'!$C16 -> 2887.28 | G31: ='12_PlantSRMC'!$C$48 -> 4760.7253 | H31: =H30+D31 -> 12469.384 | I31: =I30+E31 -> 12867.001 | J31: =J30+F31 -> 12472.552 | K31: ='11_Plants'!$J$19 -> Fuel-constrained thermal; derated by LNG availability assumption
A32: Oil | B32: ='11_Plants'!$C$20 -> 1648 | C32: ='11_Plants'!$D$20 -> 0.95 | D32: =B32*C32*'11_Plants'!$E$20*1*1 -> 1565.6 | E32: =B32*C32*'11_Plants'!$F$20*1*1 -> 1565.6 | F32: =B32*C32*'11_Plants'!$G$20*1*1 -> 1565.6 | G32: ='12_PlantSRMC'!$C$49 -> 9892.8437 | H32: =H31+D32 -> 14034.984 | I32: =I31+E32 -> 14432.601 | J32: =J31+F32 -> 14038.152 | K32: ='11_Plants'!$J$20 -> Peaker / scarcity resource
A35: Scenario 1 stack audit
A36: Cluster | B36: Cap MW | C36: Tech avail | D36: Off-peak MW | E36: Shoulder MW | F36: Peak MW | G36: SRMC | H36: Cum off | I36: Cum shoulder | J36: Cum peak | K36: Note
A37: Solar | B37: ='11_Plants'!$C$13 -> 1674 | C37: ='11_Plants'!$D$13 -> 0.98 | D37: =B37*C37*'11_Plants'!$E$13*'02_Inputs_Base'!$I$12*1 -> 0 | E37: =B37*C37*'11_Plants'!$F$13*'02_Inputs_Base'!$I$12*1 -> 585.66564 | F37: =B37*C37*'11_Plants'!$G$13*'02_Inputs_Base'!$I$12*1 -> 83.66652 | G37: ='12_PlantSRMC'!$D$41 -> 0 | H37: =D37 -> 0 | I37: =E37 -> 585.66564 | J37: =F37 -> 83.66652 | K37: ='11_Plants'!$J$13 -> Daylight-driven profile
A38: Wind | B38: ='11_Plants'!$C$14 -> 337 | C38: ='11_Plants'!$D$14 -> 0.95 | D38: =B38*C38*'11_Plants'!$E$14*'02_Inputs_Base'!$I$13*1 -> 103.40845 | E38: =B38*C38*'11_Plants'!$F$14*'02_Inputs_Base'!$I$13*1 -> 94.284175 | F38: =B38*C38*'11_Plants'!$G$14*'02_Inputs_Base'!$I$13*1 -> 88.201325 | G38: ='12_PlantSRMC'!$D$42 -> 0 | H38: =H37+D38 -> 103.40845 | I38: =I37+E38 -> 679.94981 | J38: =J37+F38 -> 171.86784 | K38: ='11_Plants'!$J$14 -> Variable RE
A39: Geothermal | B39: ='11_Plants'!$C$15 -> 714 | C39: ='11_Plants'!$D$15 -> 0.92 | D39: =B39*C39*'11_Plants'!$E$15*1*1 -> 656.88 | E39: =B39*C39*'11_Plants'!$F$15*1*1 -> 656.88 | F39: =B39*C39*'11_Plants'!$G$15*1*1 -> 656.88 | G39: ='12_PlantSRMC'!$D$43 -> 650 | H39: =H38+D39 -> 760.28845 | I39: =I38+E39 -> 1336.8298 | J39: =J38+F39 -> 828.74784 | K39: ='11_Plants'!$J$15 -> Baseload renewable
A40: Biomass | B40: ='11_Plants'!$C$16 -> 145 | C40: ='11_Plants'!$D$16 -> 0.85 | D40: =B40*C40*'11_Plants'!$E$16*1*1 -> 123.25 | E40: =B40*C40*'11_Plants'!$F$16*1*1 -> 123.25 | F40: =B40*C40*'11_Plants'!$G$16*1*1 -> 123.25 | G40: ='12_PlantSRMC'!$D$44 -> 1250 | H40: =H39+D40 -> 883.53845 | I40: =I39+E40 -> 1460.0798 | J40: =J39+F40 -> 951.99784 | K40: ='11_Plants'!$J$16 -> Stable renewable / thermal
A41: Hydro | B41: ='11_Plants'!$C$17 -> 2382 | C41: ='11_Plants'!$D$17 -> 0.93 | D41: =MIN(B41*C41*'11_Plants'!$E$17*'02_Inputs_Base'!$I$14*'02_Inputs_Base'!$L$33,'02_Inputs_Base'!$L$31) -> 780.4878 | E41: =MIN(B41*C41*'11_Plants'!$F$17*'02_Inputs_Base'!$I$14*'02_Inputs_Base'!$L$33,'02_Inputs_Base'!$L$31) -> 585.36585 | F41: =MIN(B41*C41*'11_Plants'!$G$17*'02_Inputs_Base'!$I$14*'02_Inputs_Base'!$L$33,'02_Inputs_Base'!$L$31) -> 650.4065 | G41: ='12_PlantSRMC'!$D$45 -> 1600 | H41: =H40+D41 -> 1664.0263 | I41: =I40+E41 -> 2045.4457 | J41: =J40+F41 -> 1602.4043 | K41: ='11_Plants'!$J$17 -> Peaking/flex resource
A42: ESS | B42: ='11_Plants'!$C$21 -> 341 | C42: ='11_Plants'!$D$21 -> 0.95 | D42: =B42*C42*'11_Plants'!$E$21*1*1 -> 16.1975 | E42: =B42*C42*'11_Plants'!$F$21*1*1 -> 32.395 | F42: =B42*C42*'11_Plants'!$G$21*1*1 -> 80.9875 | G42: ='12_PlantSRMC'!$D$46 -> 3200 | H42: =H41+D42 -> 1680.2238 | I42: =I41+E42 -> 2077.8407 | J42: =J41+F42 -> 1683.3918 | K42: ='11_Plants'!$J$21 -> Short-duration flexibility
A43: Coal | B43: ='11_Plants'!$C$18 -> 8589 | C43: ='11_Plants'!$D$18 -> 0.92 | D43: =B43*C43*'11_Plants'!$E$18*1*1 -> 7901.88 | E43: =B43*C43*'11_Plants'!$F$18*1*1 -> 7901.88 | F43: =B43*C43*'11_Plants'!$G$18*1*1 -> 7901.88 | G43: ='12_PlantSRMC'!$D$47 -> 3790.0463 | H43: =H42+D43 -> 9582.1038 | I43: =I42+E43 -> 9979.7207 | J43: =J42+F43 -> 9585.2718 | K43: ='11_Plants'!$J$18 -> Backbone baseload
A44: Gas | B44: ='11_Plants'!$C$19 -> 3281 | C44: ='11_Plants'!$D$19 -> 0.88 | D44: =B44*C44*'11_Plants'!$E$19*1*'03_Scenarios'!$D16 -> 2800.6616 | E44: =B44*C44*'11_Plants'!$F$19*1*'03_Scenarios'!$D16 -> 2800.6616 | F44: =B44*C44*'11_Plants'!$G$19*1*'03_Scenarios'!$D16 -> 2800.6616 | G44: ='12_PlantSRMC'!$D$48 -> 5740.1013 | H44: =H43+D44 -> 12382.765 | I44: =I43+E44 -> 12780.382 | J44: =J43+F44 -> 12385.933 | K44: ='11_Plants'!$J$19 -> Fuel-constrained thermal; derated by LNG availability assumption
A45: Oil | B45: ='11_Plants'!$C$20 -> 1648 | C45: ='11_Plants'!$D$20 -> 0.95 | D45: =B45*C45*'11_Plants'!$E$20*1*1 -> 1565.6 | E45: =B45*C45*'11_Plants'!$F$20*1*1 -> 1565.6 | F45: =B45*C45*'11_Plants'!$G$20*1*1 -> 1565.6 | G45: ='12_PlantSRMC'!$D$49 -> 10959.89 | H45: =H44+D45 -> 13948.365 | I45: =I44+E45 -> 14345.982 | J45: =J44+F45 -> 13951.533 | K45: ='11_Plants'!$J$20 -> Peaker / scarcity resource
A48: Scenario 2 stack audit
A49: Cluster | B49: Cap MW | C49: Tech avail | D49: Off-peak MW | E49: Shoulder MW | F49: Peak MW | G49: SRMC | H49: Cum off | I49: Cum shoulder | J49: Cum peak | K49: Note
A50: Solar | B50: ='11_Plants'!$C$13 -> 1674 | C50: ='11_Plants'!$D$13 -> 0.98 | D50: =B50*C50*'11_Plants'!$E$13*'02_Inputs_Base'!$I$12*1 -> 0 | E50: =B50*C50*'11_Plants'!$F$13*'02_Inputs_Base'!$I$12*1 -> 585.66564 | F50: =B50*C50*'11_Plants'!$G$13*'02_Inputs_Base'!$I$12*1 -> 83.66652 | G50: ='12_PlantSRMC'!$E$41 -> 0 | H50: =D50 -> 0 | I50: =E50 -> 585.66564 | J50: =F50 -> 83.66652 | K50: ='11_Plants'!$J$13 -> Daylight-driven profile
A51: Wind | B51: ='11_Plants'!$C$14 -> 337 | C51: ='11_Plants'!$D$14 -> 0.95 | D51: =B51*C51*'11_Plants'!$E$14*'02_Inputs_Base'!$I$13*1 -> 103.40845 | E51: =B51*C51*'11_Plants'!$F$14*'02_Inputs_Base'!$I$13*1 -> 94.284175 | F51: =B51*C51*'11_Plants'!$G$14*'02_Inputs_Base'!$I$13*1 -> 88.201325 | G51: ='12_PlantSRMC'!$E$42 -> 0 | H51: =H50+D51 -> 103.40845 | I51: =I50+E51 -> 679.94981 | J51: =J50+F51 -> 171.86784 | K51: ='11_Plants'!$J$14 -> Variable RE
A52: Geothermal | B52: ='11_Plants'!$C$15 -> 714 | C52: ='11_Plants'!$D$15 -> 0.92 | D52: =B52*C52*'11_Plants'!$E$15*1*1 -> 656.88 | E52: =B52*C52*'11_Plants'!$F$15*1*1 -> 656.88 | F52: =B52*C52*'11_Plants'!$G$15*1*1 -> 656.88 | G52: ='12_PlantSRMC'!$E$43 -> 700 | H52: =H51+D52 -> 760.28845 | I52: =I51+E52 -> 1336.8298 | J52: =J51+F52 -> 828.74784 | K52: ='11_Plants'!$J$15 -> Baseload renewable
A53: Biomass | B53: ='11_Plants'!$C$16 -> 145 | C53: ='11_Plants'!$D$16 -> 0.85 | D53: =B53*C53*'11_Plants'!$E$16*1*1 -> 123.25 | E53: =B53*C53*'11_Plants'!$F$16*1*1 -> 123.25 | F53: =B53*C53*'11_Plants'!$G$16*1*1 -> 123.25 | G53: ='12_PlantSRMC'!$E$44 -> 1300 | H53: =H52+D53 -> 883.53845 | I53: =I52+E53 -> 1460.0798 | J53: =J52+F53 -> 951.99784 | K53: ='11_Plants'!$J$16 -> Stable renewable / thermal
A54: Hydro | B54: ='11_Plants'!$C$17 -> 2382 | C54: ='11_Plants'!$D$17 -> 0.93 | D54: =MIN(B54*C54*'11_Plants'!$E$17*'02_Inputs_Base'!$I$14*'02_Inputs_Base'!$L$33,'02_Inputs_Base'!$L$31) -> 780.4878 | E54: =MIN(B54*C54*'11_Plants'!$F$17*'02_Inputs_Base'!$I$14*'02_Inputs_Base'!$L$33,'02_Inputs_Base'!$L$31) -> 585.36585 | F54: =MIN(B54*C54*'11_Plants'!$G$17*'02_Inputs_Base'!$I$14*'02_Inputs_Base'!$L$33,'02_Inputs_Base'!$L$31) -> 650.4065 | G54: ='12_PlantSRMC'!$E$45 -> 1900 | H54: =H53+D54 -> 1664.0263 | I54: =I53+E54 -> 2045.4457 | J54: =J53+F54 -> 1602.4043 | K54: ='11_Plants'!$J$17 -> Peaking/flex resource
A55: ESS | B55: ='11_Plants'!$C$21 -> 341 | C55: ='11_Plants'!$D$21 -> 0.95 | D55: =B55*C55*'11_Plants'!$E$21*1*1 -> 16.1975 | E55: =B55*C55*'11_Plants'!$F$21*1*1 -> 32.395 | F55: =B55*C55*'11_Plants'!$G$21*1*1 -> 80.9875 | G55: ='12_PlantSRMC'!$E$46 -> 3500 | H55: =H54+D55 -> 1680.2238 | I55: =I54+E55 -> 2077.8407 | J55: =J54+F55 -> 1683.3918 | K55: ='11_Plants'!$J$21 -> Short-duration flexibility
A56: Coal | B56: ='11_Plants'!$C$18 -> 8589 | C56: ='11_Plants'!$D$18 -> 0.92 | D56: =B56*C56*'11_Plants'!$E$18*1*1 -> 7901.88 | E56: =B56*C56*'11_Plants'!$F$18*1*1 -> 7901.88 | F56: =B56*C56*'11_Plants'!$G$18*1*1 -> 7901.88 | G56: ='12_PlantSRMC'!$E$47 -> 4452.9419 | H56: =H55+D56 -> 9582.1038 | I56: =I55+E56 -> 9979.7207 | J56: =J55+F56 -> 9585.2718 | K56: ='11_Plants'!$J$18 -> Backbone baseload
A57: Gas | B57: ='11_Plants'!$C$19 -> 3281 | C57: ='11_Plants'!$D$19 -> 0.88 | D57: =B57*C57*'11_Plants'!$E$19*1*'03_Scenarios'!$E16 -> 2454.188 | E57: =B57*C57*'11_Plants'!$F$19*1*'03_Scenarios'!$E16 -> 2454.188 | F57: =B57*C57*'11_Plants'!$G$19*1*'03_Scenarios'!$E16 -> 2454.188 | G57: ='12_PlantSRMC'!$E$48 -> 7983.6926 | H57: =H56+D57 -> 12036.292 | I57: =I56+E57 -> 12433.909 | J57: =J56+F57 -> 12039.46 | K57: ='11_Plants'!$J$19 -> Fuel-constrained thermal; derated by LNG availability assumption
A58: Oil | B58: ='11_Plants'!$C$20 -> 1648 | C58: ='11_Plants'!$D$20 -> 0.95 | D58: =B58*C58*'11_Plants'!$E$20*1*1 -> 1565.6 | E58: =B58*C58*'11_Plants'!$F$20*1*1 -> 1565.6 | F58: =B58*C58*'11_Plants'!$G$20*1*1 -> 1565.6 | G58: ='12_PlantSRMC'!$E$49 -> 13012.164 | H58: =H57+D58 -> 13601.892 | I58: =I57+E58 -> 13999.509 | J58: =J57+F58 -> 13605.06 | K58: ='11_Plants'!$J$20 -> Peaker / scarcity resource
A61: Scenario 3 stack audit
A62: Cluster | B62: Cap MW | C62: Tech avail | D62: Off-peak MW | E62: Shoulder MW | F62: Peak MW | G62: SRMC | H62: Cum off | I62: Cum shoulder | J62: Cum peak | K62: Note
A63: Solar | B63: ='11_Plants'!$C$13 -> 1674 | C63: ='11_Plants'!$D$13 -> 0.98 | D63: =B63*C63*'11_Plants'!$E$13*'02_Inputs_Base'!$I$12*1 -> 0 | E63: =B63*C63*'11_Plants'!$F$13*'02_Inputs_Base'!$I$12*1 -> 585.66564 | F63: =B63*C63*'11_Plants'!$G$13*'02_Inputs_Base'!$I$12*1 -> 83.66652 | G63: ='12_PlantSRMC'!$F$41 -> 0 | H63: =D63 -> 0 | I63: =E63 -> 585.66564 | J63: =F63 -> 83.66652 | K63: ='11_Plants'!$J$13 -> Daylight-driven profile
A64: Wind | B64: ='11_Plants'!$C$14 -> 337 | C64: ='11_Plants'!$D$14 -> 0.95 | D64: =B64*C64*'11_Plants'!$E$14*'02_Inputs_Base'!$I$13*1 -> 103.40845 | E64: =B64*C64*'11_Plants'!$F$14*'02_Inputs_Base'!$I$13*1 -> 94.284175 | F64: =B64*C64*'11_Plants'!$G$14*'02_Inputs_Base'!$I$13*1 -> 88.201325 | G64: ='12_PlantSRMC'!$F$42 -> 0 | H64: =H63+D64 -> 103.40845 | I64: =I63+E64 -> 679.94981 | J64: =J63+F64 -> 171.86784 | K64: ='11_Plants'!$J$14 -> Variable RE
A65: Geothermal | B65: ='11_Plants'!$C$15 -> 714 | C65: ='11_Plants'!$D$15 -> 0.92 | D65: =B65*C65*'11_Plants'!$E$15*1*1 -> 656.88 | E65: =B65*C65*'11_Plants'!$F$15*1*1 -> 656.88 | F65: =B65*C65*'11_Plants'!$G$15*1*1 -> 656.88 | G65: ='12_PlantSRMC'!$F$43 -> 800 | H65: =H64+D65 -> 760.28845 | I65: =I64+E65 -> 1336.8298 | J65: =J64+F65 -> 828.74784 | K65: ='11_Plants'!$J$15 -> Baseload renewable
A66: Biomass | B66: ='11_Plants'!$C$16 -> 145 | C66: ='11_Plants'!$D$16 -> 0.85 | D66: =B66*C66*'11_Plants'!$E$16*1*1 -> 123.25 | E66: =B66*C66*'11_Plants'!$F$16*1*1 -> 123.25 | F66: =B66*C66*'11_Plants'!$G$16*1*1 -> 123.25 | G66: ='12_PlantSRMC'!$F$44 -> 1400 | H66: =H65+D66 -> 883.53845 | I66: =I65+E66 -> 1460.0798 | J66: =J65+F66 -> 951.99784 | K66: ='11_Plants'!$J$16 -> Stable renewable / thermal
A67: Hydro | B67: ='11_Plants'!$C$17 -> 2382 | C67: ='11_Plants'!$D$17 -> 0.93 | D67: =MIN(B67*C67*'11_Plants'!$E$17*'02_Inputs_Base'!$I$14*'02_Inputs_Base'!$L$33,'02_Inputs_Base'!$L$31) -> 780.4878 | E67: =MIN(B67*C67*'11_Plants'!$F$17*'02_Inputs_Base'!$I$14*'02_Inputs_Base'!$L$33,'02_Inputs_Base'!$L$31) -> 585.36585 | F67: =MIN(B67*C67*'11_Plants'!$G$17*'02_Inputs_Base'!$I$14*'02_Inputs_Base'!$L$33,'02_Inputs_Base'!$L$31) -> 650.4065 | G67: ='12_PlantSRMC'!$F$45 -> 2300 | H67: =H66+D67 -> 1664.0263 | I67: =I66+E67 -> 2045.4457 | J67: =J66+F67 -> 1602.4043 | K67: ='11_Plants'!$J$17 -> Peaking/flex resource
A68: ESS | B68: ='11_Plants'!$C$21 -> 341 | C68: ='11_Plants'!$D$21 -> 0.95 | D68: =B68*C68*'11_Plants'!$E$21*1*1 -> 16.1975 | E68: =B68*C68*'11_Plants'!$F$21*1*1 -> 32.395 | F68: =B68*C68*'11_Plants'!$G$21*1*1 -> 80.9875 | G68: ='12_PlantSRMC'!$F$46 -> 4200 | H68: =H67+D68 -> 1680.2238 | I68: =I67+E68 -> 2077.8407 | J68: =J67+F68 -> 1683.3918 | K68: ='11_Plants'!$J$21 -> Short-duration flexibility
A69: Coal | B69: ='11_Plants'!$C$18 -> 8589 | C69: ='11_Plants'!$D$18 -> 0.92 | D69: =B69*C69*'11_Plants'!$E$18*1*1 -> 7901.88 | E69: =B69*C69*'11_Plants'!$F$18*1*1 -> 7901.88 | F69: =B69*C69*'11_Plants'!$G$18*1*1 -> 7901.88 | G69: ='12_PlantSRMC'!$F$47 -> 5527.6237 | H69: =H68+D69 -> 9582.1038 | I69: =I68+E69 -> 9979.7207 | J69: =J68+F69 -> 9585.2718 | K69: ='11_Plants'!$J$18 -> Backbone baseload
A70: Gas | B70: ='11_Plants'!$C$19 -> 3281 | C70: ='11_Plants'!$D$19 -> 0.88 | D70: =B70*C70*'11_Plants'!$E$19*1*'03_Scenarios'!$F16 -> 2021.096 | E70: =B70*C70*'11_Plants'!$F$19*1*'03_Scenarios'!$F16 -> 2021.096 | F70: =B70*C70*'11_Plants'!$G$19*1*'03_Scenarios'!$F16 -> 2021.096 | G70: ='12_PlantSRMC'!$F$48 -> 13014.425 | H70: =H69+D70 -> 11603.2 | I70: =I69+E70 -> 12000.817 | J70: =J69+F70 -> 11606.368 | K70: ='11_Plants'!$J$19 -> Fuel-constrained thermal; derated by LNG availability assumption
A71: Oil | B71: ='11_Plants'!$C$20 -> 1648 | C71: ='11_Plants'!$D$20 -> 0.95 | D71: =B71*C71*'11_Plants'!$E$20*1*1 -> 1565.6 | E71: =B71*C71*'11_Plants'!$F$20*1*1 -> 1565.6 | F71: =B71*C71*'11_Plants'!$G$20*1*1 -> 1565.6 | G71: ='12_PlantSRMC'!$F$49 -> 18378.5 | H71: =H70+D71 -> 13168.8 | I71: =I70+E71 -> 13566.417 | J71: =J70+F71 -> 13171.968 | K71: ='11_Plants'!$J$20 -> Peaker / scarcity resource

Sheet 14_ReservePricing
A1: Reserve Market Pricing Proxy (energy + scarcity linked; LNG availability feeds scarcity through peak adequacy buffer)
A4: Metric | B4: Unit | C4: Base | D4: Scenario 1 | E4: Scenario 2 | F4: Scenario 3 | G4: Audit note
A5: WESM Avg Luzon | B5: PHP/MWh | C5: ='13_MeritOrder_WESM'!C16 -> 4538.2781 | D5: ='13_MeritOrder_WESM'!D16 -> 5446.3888 | E5: ='13_MeritOrder_WESM'!E16 -> 8870.2828 | F5: ='13_MeritOrder_WESM'!F16 -> 13638.82
A6: Reserve alpha | B6: % | C6: ='03_Scenarios'!C19 -> 0.25 | D6: ='03_Scenarios'!D19 -> 0.28 | E6: ='03_Scenarios'!E19 -> 0.35 | F6: ='03_Scenarios'!F19 -> 0.45
A7: Reserve Price | B7: PHP/MW-h | C7: =C5*C6*C12 -> 1134.5695 | D7: =D5*D6*D12 -> 1524.9889 | E7: =E5*E6*E12 -> 3104.599 | F7: =F5*F6*F12 -> 6137.469
A8: Reserve volume | B8: MW-h/month | C8: ='02_Inputs_Base'!$B$9 -> 50000 | D8: ='02_Inputs_Base'!$B$9 -> 50000 | E8: ='02_Inputs_Base'!$B$9 -> 50000 | F8: ='02_Inputs_Base'!$B$9 -> 50000
A9: Reserve revenue | B9: PHP mn/month | C9: =C7*C8/1000000 -> 56.728476 | D9: =D7*D8/1000000 -> 76.249443 | E9: =E7*E8/1000000 -> 155.22995 | F9: =F7*F8/1000000 -> 306.87345 | G9: Reserve price × reserve volume / 1,000,000
A10: Reserve requirement | B10: MW | C10: 1458 | D10: 1458 | E10: 1458 | F10: 1458 | G10: Average reserve requirement proxy
A11: Peak adequacy buffer | B11: MW | C11: ='13_MeritOrder_WESM'!C17 -> 1858.1518 | D11: ='13_MeritOrder_WESM'!D17 -> 1771.5334 | E11: ='13_MeritOrder_WESM'!E17 -> 1425.0598 | F11: ='13_MeritOrder_WESM'!F17 -> 991.96785 | G11: Linked from WESM peak buffer
A12: Scarcity multiplier | B12: x | C12: =MAX(1,1+MAX(0,-C11)/C10) -> 1 | D12: =MAX(1,1+MAX(0,-D11)/D10) -> 1 | E12: =MAX(1,1+MAX(0,-E11)/E10) -> 1 | F12: =MAX(1,1+MAX(0,-F11)/F10) -> 1 | G12: Raises reserve price when peak adequacy buffer turns negative

Sheet 15_GenMargin
A1: Generation Gross Margin Sensitivity
A4: Metric | B4: Unit | C4: Base | D4: Scenario 1 | E4: Scenario 2 | F4: Scenario 3 | G4: Audit note
A5: Coal dispatch | B5: MWh/month | C5: ='12_PlantSRMC'!C31 -> 700000 | D5: ='12_PlantSRMC'!D31 -> 700000 | E5: ='12_PlantSRMC'!E31 -> 700000 | F5: ='12_PlantSRMC'!F31 -> 700000
A6: Gas dispatch | B6: MWh/month | C6: ='12_PlantSRMC'!C32 -> 250000 | D6: ='12_PlantSRMC'!D32 -> 242500 | E6: ='12_PlantSRMC'!E32 -> 212500 | F6: ='12_PlantSRMC'!F32 -> 175000
A7: Oil dispatch | B7: MWh/month | C7: ='12_PlantSRMC'!C33 -> 10000 | D7: ='12_PlantSRMC'!D33 -> 17500 | E7: ='12_PlantSRMC'!E33 -> 47500 | F7: ='12_PlantSRMC'!F33 -> 85000
A9: Coal SRMC | B9: PHP/MWh | C9: ='12_PlantSRMC'!C12 -> 3445.0582 | D9: ='12_PlantSRMC'!D12 -> 3790.0463 | E9: ='12_PlantSRMC'!E12 -> 4452.9419 | F9: ='12_PlantSRMC'!F12 -> 5527.6237
A10: Gas SRMC | B10: PHP/MWh | C10: ='12_PlantSRMC'!C21 -> 4760.7253 | D10: ='12_PlantSRMC'!D21 -> 5740.1013 | E10: ='12_PlantSRMC'!E21 -> 7983.6926 | F10: ='12_PlantSRMC'!F21 -> 13014.425
A11: Oil SRMC | B11: PHP/MWh | C11: ='12_PlantSRMC'!C28 -> 9892.8437 | D11: ='12_PlantSRMC'!D28 -> 10959.89 | E11: ='12_PlantSRMC'!E28 -> 13012.164 | F11: ='12_PlantSRMC'!F28 -> 18378.5
A13: WESM Avg Luzon | B13: PHP/MWh | C13: ='13_MeritOrder_WESM'!C16 -> 4538.2781 | D13: ='13_MeritOrder_WESM'!D16 -> 5446.3888 | E13: ='13_MeritOrder_WESM'!E16 -> 8870.2828 | F13: ='13_MeritOrder_WESM'!F16 -> 13638.82
A14: Reserve revenue | B14: PHP mn/month | C14: ='14_ReservePricing'!C9 -> 56.728476 | D14: ='14_ReservePricing'!D9 -> 76.249443 | E14: ='14_ReservePricing'!E9 -> 155.22995 | F14: ='14_ReservePricing'!F9 -> 306.87345
A16: Coal gross margin | B16: PHP mn/month | C16: =(C13-C9)*C5/1000000 -> 765.25393 | D16: =(D13-D9)*D5/1000000 -> 1159.4398 | E16: =(E13-E9)*E5/1000000 -> 3092.1386 | F16: =(F13-F9)*F5/1000000 -> 5677.8374
A17: Gas gross margin | B17: PHP mn/month | C17: =(C13-C10)*C6/1000000 -> -55.611809 | D17: =(D13-D10)*D6/1000000 -> -71.225291 | E17: =(E13-E10)*E6/1000000 -> 188.40043 | F17: =(F13-F10)*F6/1000000 -> 109.26906
A18: Oil gross margin | B18: PHP mn/month | C18: =(C13-C11)*C7/1000000 -> -53.545656 | D18: =(D13-D11)*D7/1000000 -> -96.486265 | E18: =(E13-E11)*E7/1000000 -> -196.73935 | F18: =(F13-F11)*F7/1000000 -> -402.8728
A19: Energy gross margin | B19: PHP mn/month | C19: =SUM(C16:C18) -> 656.09647 | D19: =SUM(D16:D18) -> 991.7282 | E19: =SUM(E16:E18) -> 3083.7997 | F19: =SUM(F16:F18) -> 5384.2336
A20: Total generation gross margin | B20: PHP mn/month | C20: =C19+C14 -> 712.82494 | D20: =D19+D14 -> 1067.9776 | E20: =E19+E14 -> 3239.0297 | F20: =F19+F14 -> 5691.1071 | G20: Energy margin + reserve revenue

Sheet 20_SupplyWholesale_Contracts
A1: Supply & Wholesale Exposure Inputs
A3: Input | B3: Value | C3: Unit | D3: Type | E3: Comment
A4: BCQ_volume_MWh | B4: 300000 | C4: MWh/month | D4: Input | E4: Illustrative BCQ volume exposure
A5: BCQ_sell_price_PHP_MWh | B5: 5800 | C5: PHP/MWh | D5: Input | E5: Illustrative bilateral contract sell price
A6: Spot_sales_volume_MWh | B6: 120000 | C6: MWh/month | D6: Input | E6: Illustrative spot sales volume
A7: Imbalance_volume_MWh | B7: 30000 | C7: MWh/month | D7: Input | E7: Illustrative imbalance volume (purchase if short)
A8: Imbalance_contract_price_PHP_MWh | B8: 5900 | C8: PHP/MWh | D8: Input | E8: Reference price for imbalance exposure
A9: Repricing_beta | B9: 0.3 | C9: % | D9: Input | E9: Fraction of price shock recoverable through repricing
A10: Wholesale_opex_PHP_mn | B10: 50 | C10: PHP mn/month | D10: Input | E10: Illustrative monthly wholesale opex

Sheet 21_SupplyWholesale_Margin
A1: Scenario-based Supply & Wholesale Margin Sensitivity
A4: Metric | B4: Unit | C4: Base | D4: Scenario 1 | E4: Scenario 2 | F4: Scenario 3 | G4: Audit note
A5: WESM Avg Luzon | B5: PHP/MWh | C5: ='13_MeritOrder_WESM'!C16 -> 4538.2781 | D5: ='13_MeritOrder_WESM'!D16 -> 5446.3888 | E5: ='13_MeritOrder_WESM'!E16 -> 8870.2828 | F5: ='13_MeritOrder_WESM'!F16 -> 13638.82
A6: Weighted fleet SRMC | B6: PHP/MWh | C6: ='12_PlantSRMC'!C35 -> 3854.8442 | D6: ='12_PlantSRMC'!D35 -> 4413.3386 | E6: ='12_PlantSRMC'!E35 -> 5657.9915 | F6: ='12_PlantSRMC'!F35 -> 8030.2433
A7: BCQ exposure margin | B7: PHP mn/month | C7: =('20_SupplyWholesale_Contracts'!$B$5-C5)*'20_SupplyWholesale_Contracts'!$B$4/1000000 -> 378.51658 | D7: =('20_SupplyWholesale_Contracts'!$B$5-D5)*'20_SupplyWholesale_Contracts'!$B$4/1000000 -> 106.08336 | E7: =('20_SupplyWholesale_Contracts'!$B$5-E5)*'20_SupplyWholesale_Contracts'!$B$4/1000000 -> -921.08485 | F7: =('20_SupplyWholesale_Contracts'!$B$5-F5)*'20_SupplyWholesale_Contracts'!$B$4/1000000 -> -2351.646
A8: Spot sales margin | B8: PHP mn/month | C8: =(C5-C6)*'20_SupplyWholesale_Contracts'!$B$6/1000000 -> 82.012059 | D8: =(D5-D6)*'20_SupplyWholesale_Contracts'!$B$6/1000000 -> 123.96603 | E8: =(E5-E6)*'20_SupplyWholesale_Contracts'!$B$6/1000000 -> 385.47497 | F8: =(F5-F6)*'20_SupplyWholesale_Contracts'!$B$6/1000000 -> 673.02921
A9: Imbalance exposure | B9: PHP mn/month | C9: =-(C5-'20_SupplyWholesale_Contracts'!$B$8)*'20_SupplyWholesale_Contracts'!$B$7/1000000 -> 40.851658 | D9: =-(D5-'20_SupplyWholesale_Contracts'!$B$8)*'20_SupplyWholesale_Contracts'!$B$7/1000000 -> 13.608336 | E9: =-(E5-'20_SupplyWholesale_Contracts'!$B$8)*'20_SupplyWholesale_Contracts'!$B$7/1000000 -> -89.108485 | F9: =-(F5-'20_SupplyWholesale_Contracts'!$B$8)*'20_SupplyWholesale_Contracts'!$B$7/1000000 -> -232.1646
A10: Contract repricing recovery | B10: PHP mn/month | C10: =IF(C5>$C$5,(C5-$C$5)*'20_SupplyWholesale_Contracts'!$B$9*'20_SupplyWholesale_Contracts'!$B$4/1000000,0) -> 0 | D10: =IF(D5>$C$5,(D5-$C$5)*'20_SupplyWholesale_Contracts'!$B$9*'20_SupplyWholesale_Contracts'!$B$4/1000000,0) -> 81.729968 | E10: =IF(E5>$C$5,(E5-$C$5)*'20_SupplyWholesale_Contracts'!$B$9*'20_SupplyWholesale_Contracts'!$B$4/1000000,0) -> 389.88043 | F10: =IF(F5>$C$5,(F5-$C$5)*'20_SupplyWholesale_Contracts'!$B$9*'20_SupplyWholesale_Contracts'!$B$4/1000000,0) -> 819.04877
A11: Wholesale opex | B11: PHP mn/month | C11: ='20_SupplyWholesale_Contracts'!$B$10 -> 50 | D11: ='20_SupplyWholesale_Contracts'!$B$10 -> 50 | E11: ='20_SupplyWholesale_Contracts'!$B$10 -> 50 | F11: ='20_SupplyWholesale_Contracts'!$B$10 -> 50
A12: Total supply & wholesale margin | B12: PHP mn/month | C12: =SUM(C7:C10)-C11 -> 451.3803 | D12: =SUM(D7:D10)-D11 -> 275.38769 | E12: =SUM(E7:E10)-E11 -> -284.83794 | F12: =SUM(F7:F10)-F11 -> -1141.7326 | G12: BCQ + spot + imbalance + repricing - opex

Sheet 22_MarginBridge
A1: Supply & Wholesale Margin Bridge (Base to Scenario)
A4: Driver | B4: S1 | C4: S2 | D4: S3 | E4: Audit note
A5: Base margin | B5: ='21_SupplyWholesale_Margin'!$C$12 -> 451.3803 | C5: ='21_SupplyWholesale_Margin'!$C$12 -> 451.3803 | D5: ='21_SupplyWholesale_Margin'!$C$12 -> 451.3803 | E5: Starting point
A6: BCQ / WESM price effect | B6: =-( '21_SupplyWholesale_Margin'!D5-'21_SupplyWholesale_Margin'!$C$5 )*'20_SupplyWholesale_Contracts'!$B$4/1000000 -> -272.43323 | C6: =-( '21_SupplyWholesale_Margin'!E5-'21_SupplyWholesale_Margin'!$C$5 )*'20_SupplyWholesale_Contracts'!$B$4/1000000 -> -1299.6014 | D6: =-( '21_SupplyWholesale_Margin'!F5-'21_SupplyWholesale_Margin'!$C$5 )*'20_SupplyWholesale_Contracts'!$B$4/1000000 -> -2730.1626 | E6: ΔWESM × BCQ volume (negative to margin)
A7: Spot / WESM price effect | B7: =( '21_SupplyWholesale_Margin'!D5-'21_SupplyWholesale_Margin'!$C$5 )*'20_SupplyWholesale_Contracts'!$B$6/1000000 -> 108.97329 | C7: =( '21_SupplyWholesale_Margin'!E5-'21_SupplyWholesale_Margin'!$C$5 )*'20_SupplyWholesale_Contracts'!$B$6/1000000 -> 519.84057 | D7: =( '21_SupplyWholesale_Margin'!F5-'21_SupplyWholesale_Margin'!$C$5 )*'20_SupplyWholesale_Contracts'!$B$6/1000000 -> 1092.065 | E7: ΔWESM × spot sales volume
A8: Fuel / SRMC effect on spot | B8: =-( '21_SupplyWholesale_Margin'!D6-'21_SupplyWholesale_Margin'!$C$6 )*'20_SupplyWholesale_Contracts'!$B$6/1000000 -> -67.019323 | C8: =-( '21_SupplyWholesale_Margin'!E6-'21_SupplyWholesale_Margin'!$C$6 )*'20_SupplyWholesale_Contracts'!$B$6/1000000 -> -216.37767 | D8: =-( '21_SupplyWholesale_Margin'!F6-'21_SupplyWholesale_Margin'!$C$6 )*'20_SupplyWholesale_Contracts'!$B$6/1000000 -> -501.04789 | E8: Δweighted fleet SRMC × spot volume
A9: Imbalance effect | B9: =-( '21_SupplyWholesale_Margin'!D5-'21_SupplyWholesale_Margin'!$C$5 )*'20_SupplyWholesale_Contracts'!$B$7/1000000 -> -27.243323 | C9: =-( '21_SupplyWholesale_Margin'!E5-'21_SupplyWholesale_Margin'!$C$5 )*'20_SupplyWholesale_Contracts'!$B$7/1000000 -> -129.96014 | D9: =-( '21_SupplyWholesale_Margin'!F5-'21_SupplyWholesale_Margin'!$C$5 )*'20_SupplyWholesale_Contracts'!$B$7/1000000 -> -273.01626 | E9: ΔWESM × imbalance volume
A10: Contract repricing recovery | B10: ='21_SupplyWholesale_Margin'!D10 -> 81.729968 | C10: ='21_SupplyWholesale_Margin'!E10 -> 389.88043 | D10: ='21_SupplyWholesale_Margin'!F10 -> 819.04877 | E10: Offset from repricing clauses
A11: Bridge-implied scenario margin | B11: =SUM(B5:B10) -> 275.38769 | C11: =SUM(C5:C10) -> -284.83794 | D11: =SUM(D5:D10) -> -1141.7326 | E11: Bridge sum
A12: Actual scenario margin | B12: ='21_SupplyWholesale_Margin'!D12 -> 275.38769 | C12: ='21_SupplyWholesale_Margin'!E12 -> -284.83794 | D12: ='21_SupplyWholesale_Margin'!F12 -> -1141.7326 | E12: Direct model result
A13: Reconciliation | B13: =B12-B11 -> 0 | C13: =C12-C11 -> 0 | D13: =D12-D11 -> 0 | E13: Should tie to zero
A14: Status | B14: =IF(AND(B13<0.01,B13>-0.01),"OK","FLAG") -> OK | C14: =IF(AND(C13<0.01,C13>-0.01),"OK","FLAG") -> OK | D14: =IF(AND(D13<0.01,D13>-0.01),"OK","FLAG") -> OK | E14: OK if reconciliation within tolerance

Sheet 30_Retail_Inputs
A1: Retail Portfolio Assumptions
A3: Segment | B3: Volume (MWh/month) | C3: Base tariff (PHP/kWh) | D3: Procurement link to WESM (x) | E3: Pass-through % | F3: Bad debt base % | G3: Attrition S1 % | H3: Attrition S2 % | I3: Attrition S3 % | J3: Opex (PHP mn/month) | K3: Comment
A5: Fixed C&I | B5: 250000 | C5: 7.2 | D5: 1 | E5: 0.2 | F5: 0.01 | G5: 0.01 | H5: 0.03 | I5: 0.06 | J5: 35 | K5: Fixed-price portfolio; low pass-through
A6: Indexed C&I | B6: 180000 | C6: 6.8 | D6: 0.95 | E6: 0.8 | F6: 0.007 | G6: 0.005 | H6: 0.015 | I6: 0.03 | J6: 20 | K6: Indexed contracts; higher pass-through
A7: Other Retail | B7: 120000 | C7: 6.2 | D7: 0.9 | E7: 0.3 | F7: 0.015 | G7: 0.005 | H7: 0.02 | I7: 0.04 | J7: 15 | K7: Higher regulatory and credit sensitivity

Sheet 31_Retail_EBIT
A1: Retail EBIT Sensitivity by Scenario
A2: Each segment block shows the full chain from volume attrition to procurement cost to tariff recovery to bad debt to EBIT. The top summary is linked into the deck-ready output sheet.
A5: Metric | B5: Unit | C5: Base | D5: Scenario 1 | E5: Scenario 2 | F5: Scenario 3 | G5: Audit note
A6: Fixed C&I EBIT | B6: PHP mn/month | C6: =C22 -> 612.43049 | D6: =D22 -> 424.78726 | E6: =E22 -> -252.43653 | F6: =F22 -> -1147.9537
A7: Indexed C&I EBIT | B7: PHP mn/month | C7: =C32 -> 419.38645 | D7: =D32 -> 384.95264 | E7: =E32 -> 260.89847 | F7: =F32 -> 90.820983
A8: Other Retail EBIT | B8: PHP mn/month | C8: =C42 -> 227.70597 | D8: =D42 -> 157.16623 | E8: =E42 -> -102.11097 | F8: =F42 -> -451.21701
A9: Portfolio EBIT | B9: PHP mn/month | C9: =SUM(C6:C8) -> 1259.5229 | D9: =SUM(D6:D8) -> 966.90613 | E9: =SUM(E6:E8) -> -93.649037 | F9: =SUM(F6:F8) -> -1508.3497 | G9: Sum of segment EBITs
A10: Fixed-price margin at risk | B10: PHP mn/month | C10: =IF($C$6>C6,$C$6-C6,0) -> 0 | D10: =IF($C$6>D6,$C$6-D6,0) -> 187.64322 | E10: =IF($C$6>E6,$C$6-E6,0) -> 864.86702 | F10: =IF($C$6>F6,$C$6-F6,0) -> 1760.3841
A14: Fixed C&I — detailed build-up
A15: Volume after attrition | B15: MWh/month | C15: ='30_Retail_Inputs'!$B$5*(1-0) -> 250000 | D15: ='30_Retail_Inputs'!$B$5*(1-'30_Retail_Inputs'!$G$5) -> 247500 | E15: ='30_Retail_Inputs'!$B$5*(1-'30_Retail_Inputs'!$H$5) -> 242500 | F15: ='30_Retail_Inputs'!$B$5*(1-'30_Retail_Inputs'!$I$5) -> 235000
A16: Procurement cost | B16: PHP/MWh | C16: ='13_MeritOrder_WESM'!C16*'30_Retail_Inputs'!$D$5 -> 4538.2781 | D16: ='13_MeritOrder_WESM'!D16*'30_Retail_Inputs'!$D$5 -> 5446.3888 | E16: ='13_MeritOrder_WESM'!E16*'30_Retail_Inputs'!$D$5 -> 8870.2828 | F16: ='13_MeritOrder_WESM'!F16*'30_Retail_Inputs'!$D$5 -> 13638.82
A17: Tariff | B17: PHP/kWh | C17: ='30_Retail_Inputs'!$C$5+'30_Retail_Inputs'!$E$5*IF(C16>$C$16,C16-$C$16,0)/1000 -> 7.2 | D17: ='30_Retail_Inputs'!$C$5+'30_Retail_Inputs'!$E$5*IF(D16>$C$16,D16-$C$16,0)/1000 -> 7.3816222 | E17: ='30_Retail_Inputs'!$C$5+'30_Retail_Inputs'!$E$5*IF(E16>$C$16,E16-$C$16,0)/1000 -> 8.066401 | F17: ='30_Retail_Inputs'!$C$5+'30_Retail_Inputs'!$E$5*IF(F16>$C$16,F16-$C$16,0)/1000 -> 9.0201084
A18: Revenue | B18: PHP mn/month | C18: =C15*1000*C17/1000000 -> 1800 | D18: =D15*1000*D17/1000000 -> 1826.9515 | E18: =E15*1000*E17/1000000 -> 1956.1022 | F18: =F15*1000*F17/1000000 -> 2119.7255
A19: Energy cost | B19: PHP mn/month | C19: =C15*C16/1000000 -> 1134.5695 | D19: =D15*D16/1000000 -> 1347.9812 | E19: =E15*E16/1000000 -> 2151.0436 | F19: =F15*F16/1000000 -> 3205.1227
A20: Bad debt | B20: PHP mn/month | C20: =C18*'30_Retail_Inputs'!$F$5*'03_Scenarios'!C20 -> 18 | D20: =D18*'30_Retail_Inputs'!$F$5*'03_Scenarios'!D20 -> 19.182991 | E20: =E18*'30_Retail_Inputs'!$F$5*'03_Scenarios'!E20 -> 22.495176 | F20: =F18*'30_Retail_Inputs'!$F$5*'03_Scenarios'!F20 -> 27.556431
A21: Opex | B21: PHP mn/month | C21: ='30_Retail_Inputs'!$J$5 -> 35 | D21: ='30_Retail_Inputs'!$J$5 -> 35 | E21: ='30_Retail_Inputs'!$J$5 -> 35 | F21: ='30_Retail_Inputs'!$J$5 -> 35
A22: EBIT | B22: PHP mn/month | C22: =C18-C19-C20-C21 -> 612.43049 | D22: =D18-D19-D20-D21 -> 424.78726 | E22: =E18-E19-E20-E21 -> -252.43653 | F22: =F18-F19-F20-F21 -> -1147.9537
A24: Indexed C&I — detailed build-up
A25: Volume after attrition | B25: MWh/month | C25: ='30_Retail_Inputs'!$B$6*(1-0) -> 180000 | D25: ='30_Retail_Inputs'!$B$6*(1-'30_Retail_Inputs'!$G$6) -> 179100 | E25: ='30_Retail_Inputs'!$B$6*(1-'30_Retail_Inputs'!$H$6) -> 177300 | F25: ='30_Retail_Inputs'!$B$6*(1-'30_Retail_Inputs'!$I$6) -> 174600
A26: Procurement cost | B26: PHP/MWh | C26: ='13_MeritOrder_WESM'!C16*'30_Retail_Inputs'!$D$6 -> 4311.3642 | D26: ='13_MeritOrder_WESM'!D16*'30_Retail_Inputs'!$D$6 -> 5174.0694 | E26: ='13_MeritOrder_WESM'!E16*'30_Retail_Inputs'!$D$6 -> 8426.7687 | F26: ='13_MeritOrder_WESM'!F16*'30_Retail_Inputs'!$D$6 -> 12956.879
A27: Tariff | B27: PHP/kWh | C27: ='30_Retail_Inputs'!$C$6+'30_Retail_Inputs'!$E$6*IF(C26>$C$26,C26-$C$26,0)/1000 -> 6.8 | D27: ='30_Retail_Inputs'!$C$6+'30_Retail_Inputs'!$E$6*IF(D26>$C$26,D26-$C$26,0)/1000 -> 7.4901642 | E27: ='30_Retail_Inputs'!$C$6+'30_Retail_Inputs'!$E$6*IF(E26>$C$26,E26-$C$26,0)/1000 -> 10.092324 | F27: ='30_Retail_Inputs'!$C$6+'30_Retail_Inputs'!$E$6*IF(F26>$C$26,F26-$C$26,0)/1000 -> 13.716412
A28: Revenue | B28: PHP mn/month | C28: =C25*1000*C27/1000000 -> 1224 | D28: =D25*1000*D27/1000000 -> 1341.4884 | E28: =E25*1000*E27/1000000 -> 1789.369 | F28: =F25*1000*F27/1000000 -> 2394.8855
A29: Energy cost | B29: PHP mn/month | C29: =C25*C26/1000000 -> 776.04555 | D29: =D25*D26/1000000 -> 926.67582 | E29: =E25*E26/1000000 -> 1494.0661 | F29: =F25*F26/1000000 -> 2262.2711
A30: Bad debt | B30: PHP mn/month | C30: =C28*'30_Retail_Inputs'!$F$6*'03_Scenarios'!C20 -> 8.568 | D30: =D28*'30_Retail_Inputs'!$F$6*'03_Scenarios'!D20 -> 9.8599398 | E30: =E28*'30_Retail_Inputs'!$F$6*'03_Scenarios'!E20 -> 14.40442 | F30: =F28*'30_Retail_Inputs'!$F$6*'03_Scenarios'!F20 -> 21.793458
A31: Opex | B31: PHP mn/month | C31: ='30_Retail_Inputs'!$J$6 -> 20 | D31: ='30_Retail_Inputs'!$J$6 -> 20 | E31: ='30_Retail_Inputs'!$J$6 -> 20 | F31: ='30_Retail_Inputs'!$J$6 -> 20
A32: EBIT | B32: PHP mn/month | C32: =C28-C29-C30-C31 -> 419.38645 | D32: =D28-D29-D30-D31 -> 384.95264 | E32: =E28-E29-E30-E31 -> 260.89847 | F32: =F28-F29-F30-F31 -> 90.820983
A34: Other Retail — detailed build-up
A35: Volume after attrition | B35: MWh/month | C35: ='30_Retail_Inputs'!$B$7*(1-0) -> 120000 | D35: ='30_Retail_Inputs'!$B$7*(1-'30_Retail_Inputs'!$G$7) -> 119400 | E35: ='30_Retail_Inputs'!$B$7*(1-'30_Retail_Inputs'!$H$7) -> 117600 | F35: ='30_Retail_Inputs'!$B$7*(1-'30_Retail_Inputs'!$I$7) -> 115200
A36: Procurement cost | B36: PHP/MWh | C36: ='13_MeritOrder_WESM'!C16*'30_Retail_Inputs'!$D$7 -> 4084.4502 | D36: ='13_MeritOrder_WESM'!D16*'30_Retail_Inputs'!$D$7 -> 4901.7499 | E36: ='13_MeritOrder_WESM'!E16*'30_Retail_Inputs'!$D$7 -> 7983.2546 | F36: ='13_MeritOrder_WESM'!F16*'30_Retail_Inputs'!$D$7 -> 12274.938
A37: Tariff | B37: PHP/kWh | C37: ='30_Retail_Inputs'!$C$7+'30_Retail_Inputs'!$E$7*IF(C36>$C$36,C36-$C$36,0)/1000 -> 6.2 | D37: ='30_Retail_Inputs'!$C$7+'30_Retail_Inputs'!$E$7*IF(D36>$C$36,D36-$C$36,0)/1000 -> 6.4451899 | E37: ='30_Retail_Inputs'!$C$7+'30_Retail_Inputs'!$E$7*IF(E36>$C$36,E36-$C$36,0)/1000 -> 7.3696413 | F37: ='30_Retail_Inputs'!$C$7+'30_Retail_Inputs'!$E$7*IF(F36>$C$36,F36-$C$36,0)/1000 -> 8.6571463
A38: Revenue | B38: PHP mn/month | C38: =C35*1000*C37/1000000 -> 744 | D38: =D35*1000*D37/1000000 -> 769.55567 | E38: =E35*1000*E37/1000000 -> 866.66982 | F38: =F35*1000*F37/1000000 -> 997.30326
A39: Energy cost | B39: PHP mn/month | C39: =C35*C36/1000000 -> 490.13403 | D39: =D35*D36/1000000 -> 585.26894 | E39: =E35*E36/1000000 -> 938.83074 | F39: =F35*F36/1000000 -> 1414.0729
A40: Bad debt | B40: PHP mn/month | C40: =C38*'30_Retail_Inputs'!$F$7*'03_Scenarios'!C20 -> 11.16 | D40: =D38*'30_Retail_Inputs'!$F$7*'03_Scenarios'!D20 -> 12.120502 | E40: =E38*'30_Retail_Inputs'!$F$7*'03_Scenarios'!E20 -> 14.950054 | F40: =F38*'30_Retail_Inputs'!$F$7*'03_Scenarios'!F20 -> 19.447414
A41: Opex | B41: PHP mn/month | C41: ='30_Retail_Inputs'!$J$7 -> 15 | D41: ='30_Retail_Inputs'!$J$7 -> 15 | E41: ='30_Retail_Inputs'!$J$7 -> 15 | F41: ='30_Retail_Inputs'!$J$7 -> 15
A42: EBIT | B42: PHP mn/month | C42: =C38-C39-C40-C41 -> 227.70597 | D42: =D38-D39-D40-D41 -> 157.16623 | E42: =E38-E39-E40-E41 -> -102.11097 | F42: =F38-F39-F40-F41 -> -451.21701

Sheet 40_Liquidity_Inputs
A1: Liquidity Stress Inputs
A3: Input | B3: Value | C3: Unit | D3: Type | E3: Comment
A4: Coal_inventory_days | B4: 20 | C4: days | D4: Input | E4: Target on-hand coal days
A5: Gas_inventory_days | B5: 10 | C5: days | D5: Input | E5: LNG / gas working-stock days
A6: Oil_inventory_days | B6: 7 | C6: days | D6: Input | E6: Oil product inventory days
A7: Coal_payables_days | B7: 15 | C7: days | D7: Input | E7: Effective supplier terms
A8: Gas_payables_days | B8: 0 | C8: days | D8: Input | E8: Effective LNG payment terms
A9: Oil_payables_days | B9: 5 | C9: days | D9: Input | E9: Effective oil payment terms
A10: LC_margin_Base | B10: 0.2 | C10: % | D10: Input | E10: LC / collateral margin base case
A11: LC_margin_30d | B11: 0.25 | C11: % | D11: Input | E11: LC / collateral margin for 30-day stress
A12: LC_margin_90d | B12: 0.3 | C12: % | D12: Input | E12: LC / collateral margin for 90-day stress
A13: LC_margin_180d | B13: 0.35 | C13: % | D13: Input | E13: LC / collateral margin for 180-day stress
A14: Starting_cash_PHP_mn | B14: 10000 | C14: PHP mn | D14: Input | E14: Illustrative starting cash
A15: Undrawn_facilities_PHP_mn | B15: 15000 | C15: PHP mn | D15: Input | E15: Illustrative undrawn committed facilities
... A20: Covenant_max_ND_EBITDA | B20: 4.5 | C20: x | D20: Input | E20: Maximum net debt / EBITDA covenant
A23: AGRA-style regulatory recovery inputs
A24: Parameter | B24: Base | C24: 30 Days | D24: 90 Days | E24: 180 Days | F24: Unit | G24: Comment
A25: ImmediateRecovery_pct | B25: 1 | C25: 0.9 | D25: 0.75 | E25: 0.6 | F25: % | G25: Scenario share of monthly generation cost shock billed / recovered immediately
A26: Disallowance_pct | B26: 0.005 | C26: 0.01 | D26: 0.02 | E26: 0.04 | F26: % | G26: Scenario share of generation cost adjustment flagged / refunded after verification
A27: CustomerCollectionLag_days | B27: 30 | C27: 30 | D27: 30 | E27: 30 | F27: days | G27: Placeholder monthly billing / collection lag
A28: RefundLag_months | B28: 1 | C28: 1 | D28: 1 | E28: 1 | F28: months | G28: Refund timing lag after ERC verification / refund order
A29: TrueUpHorizon_months | B29: 36 | C29: 36 | D29: 36 | E29: 36 | F29: months | G29: Regulatory receivable amortization / staggering horizon
A30: CarryingCost_pct_pa | B30: 0.07 | C30: 0.07 | D30: 0.07 | E30: 0.07 | F30: % | G30: Carrying cost on deferred regulatory receivable balance

Sheet 41_Liquidity_Model
A1: Module 3 — 30 / 90 / 180-Day Liquidity Stress
A2: Base/30/90/180 columns intentionally mirror the RFP sample structure. 30 Days maps to S1, 90 Days to S2, 180 Days to S3 via 04_HorizonMap. This version adds an auditable AGRA-style recovery engine for billed generation charge adjustments, refunds, and deferred regulatory receivables.
A5: Metric | B5: Unit | C5: Base | D5: 30 Days | E5: 90 Days | F5: 180 Days | G5: Audit note
A6: Coal fuel spend | B6: PHP mn/month | C6: ='12_PlantSRMC'!C31*'12_PlantSRMC'!C10/1000000 -> 182 | D6: ='12_PlantSRMC'!D31*'12_PlantSRMC'!D10/1000000 -> 182 | E6: ='12_PlantSRMC'!E31*'12_PlantSRMC'!E10/1000000 -> 182 | F6: ='12_PlantSRMC'!F31*'12_PlantSRMC'!F10/1000000 -> 182
A7: Gas fuel spend | B7: PHP mn/month | C7: ='12_PlantSRMC'!C32*'12_PlantSRMC'!C19/1000000 -> 1145.1813 | D7: ='12_PlantSRMC'!D32*'12_PlantSRMC'!D19/1000000 -> 1348.3246 | E7: ='12_PlantSRMC'!E32*'12_PlantSRMC'!E19/1000000 -> 1658.2847 | F7: ='12_PlantSRMC'!F32*'12_PlantSRMC'!F19/1000000 -> 2246.0244
A8: Oil fuel spend | B8: PHP mn/month | C8: ='12_PlantSRMC'!C33*'12_PlantSRMC'!C26/1000000 -> 94.428437 | D8: ='12_PlantSRMC'!D33*'12_PlantSRMC'!D26/1000000 -> 183.92307 | E8: ='12_PlantSRMC'!E33*'12_PlantSRMC'!E26/1000000 -> 596.70278 | F8: ='12_PlantSRMC'!F33*'12_PlantSRMC'!F26/1000000 -> 1523.9225
A9: Total fuel spend | B9: PHP mn/month | C9: =SUM(C6:C8) -> 1421.6098 | D9: =SUM(D6:D8) -> 1714.2476 | E9: =SUM(E6:E8) -> 2436.9874 | F9: =SUM(F6:F8) -> 3951.9469
A10: Coal net WC days | B10: days | C10: ='40_Liquidity_Inputs'!$B$4+'03_Scenarios'!C17-'40_Liquidity_Inputs'!$B$7 -> 5 | D10: ='40_Liquidity_Inputs'!$B$4+'03_Scenarios'!D17-'40_Liquidity_Inputs'!$B$7 -> 10 | E10: ='40_Liquidity_Inputs'!$B$4+'03_Scenarios'!E17-'40_Liquidity_Inputs'!$B$7 -> 19 | F10: ='40_Liquidity_Inputs'!$B$4+'03_Scenarios'!F17-'40_Liquidity_Inputs'!$B$7 -> 33
A11: Coal working capital | B11: PHP mn | C11: =C6/30*C10 -> 30.333333 | D11: =D6/30*D10 -> 60.666667 | E11: =E6/30*E10 -> 115.26667 | F11: =F6/30*F10 -> 200.2
A12: Gas net WC days | B12: days | C12: ='40_Liquidity_Inputs'!$B$5-'40_Liquidity_Inputs'!$B$8 -> 10 | D12: ='40_Liquidity_Inputs'!$B$5-'40_Liquidity_Inputs'!$B$8 -> 10 | E12: ='40_Liquidity_Inputs'!$B$5-'40_Liquidity_Inputs'!$B$8 -> 10 | F12: ='40_Liquidity_Inputs'!$B$5-'40_Liquidity_Inputs'!$B$8 -> 10
A13: Gas working capital | B13: PHP mn | C13: =C7/30*C12 -> 381.72711 | D13: =D7/30*D12 -> 449.44153 | E13: =E7/30*E12 -> 552.76156 | F13: =F7/30*F12 -> 748.67481
A14: Oil net WC days | B14: days | C14: ='40_Liquidity_Inputs'!$B$6-'40_Liquidity_Inputs'!$B$9 -> 2 | D14: ='40_Liquidity_Inputs'!$B$6-'40_Liquidity_Inputs'!$B$9 -> 2 | E14: ='40_Liquidity_Inputs'!$B$6-'40_Liquidity_Inputs'!$B$9 -> 2 | F14: ='40_Liquidity_Inputs'!$B$6-'40_Liquidity_Inputs'!$B$9 -> 2
A15: Oil working capital | B15: PHP mn | C15: =C8/30*C14 -> 6.2952291 | D15: =D8/30*D14 -> 12.261538 | E15: =E8/30*E14 -> 39.780185 | F15: =F8/30*F14 -> 101.59483
A16: Working Capital | B16: PHP mn | C16: =SUM(C11,C13,C15) -> 418.35567 | D16: =SUM(D11,D13,D15) -> 522.36973 | E16: =SUM(E11,E13,E15) -> 707.80841 | F16: =SUM(F11,F13,F15) -> 1050.4696 | G16: Sum of coal + gas + oil working capital
A17: LC margin | B17: % | C17: ='40_Liquidity_Inputs'!$B$10 -> 0.2 | D17: ='40_Liquidity_Inputs'!$B$11 -> 0.25 | E17: ='40_Liquidity_Inputs'!$B$12 -> 0.3 | F17: ='40_Liquidity_Inputs'!$B$13 -> 0.35
A18: LC Requirements | B18: PHP mn | C18: =C9*C17 -> 284.32195 | D18: =D9*D17 -> 428.56191 | E18: =E9*E17 -> 731.09623 | F18: =F9*F17 -> 1383.1814 | G18: Total fuel spend × LC margin
A19: Operating contribution | B19: PHP mn/month | C19: ='15_GenMargin'!C20+'21_SupplyWholesale_Margin'!C12+'31_Retail_EBIT'!C9 -> 2423.7282 | D19: ='15_GenMargin'!D20+'21_SupplyWholesale_Margin'!D12+'31_Retail_EBIT'!D9 -> 2310.2715 | E19: ='15_GenMargin'!E20+'21_SupplyWholesale_Margin'!E12+'31_Retail_EBIT'!E9 -> 2860.5427 | F19: ='15_GenMargin'!F20+'21_SupplyWholesale_Margin'!F12+'31_Retail_EBIT'!F9 -> 3041.0248
A20: Cash flow compression | B20: PHP mn/month | C20: =$C$19-C19 -> 0 | D20: =$C$19-D19 -> 113.45669 | E20: =$C$19-E19 -> -436.81454 | F20: =$C$19-F19 -> -617.29663
A21: Horizon months | B21: months | C21: 0 | D21: 1 | E21: 3 | F21: 6
A22: Starting liquidity | B22: PHP mn | C22: ='40_Liquidity_Inputs'!$B$14+'40_Liquidity_Inputs'!$B$15 -> 25000 | D22: ='40_Liquidity_Inputs'!$B$14+'40_Liquidity_Inputs'!$B$15 -> 25000 | E22: ='40_Liquidity_Inputs'!$B$14+'40_Liquidity_Inputs'!$B$15 -> 25000 | F22: ='40_Liquidity_Inputs'!$B$14+'40_Liquidity_Inputs'!$B$15 -> 25000
A23: Debt service cumulative | B23: PHP mn | C23: =C21*'40_Liquidity_Inputs'!$B$17 -> 0 | D23: =D21*'40_Liquidity_Inputs'!$B$17 -> 300 | E23: =E21*'40_Liquidity_Inputs'!$B$17 -> 900 | F23: =F21*'40_Liquidity_Inputs'!$B$17 -> 1800
A24: Cash Balance | B24: PHP mn | C24: =C22-C16-C18-C20*C21-C23-C42-C43 -> 24297.322 | D24: =D22-D16-D18-D20*D21-D23-D42-D43 -> 23606.348 | E24: =E22-E16-E18-E20*E21-E23-E42-E43 -> 23185.98 | F24: =F22-F16-F18-F20*F21-F23-F42-F43 -> 18214.824 | G24: Starting liquidity less WC, LC, burn, debt service, deferred regulatory receivable, and refund provision
A25: Stress EBITDA annual | B25: PHP mn | C25: ='40_Liquidity_Inputs'!$B$19+(C19-$C$19)*12 -> 18000 | D25: ='40_Liquidity_Inputs'!$B$19+(D19-$C$19)*12 -> 16638.52 | E25: ='40_Liquidity_Inputs'!$B$19+(E19-$C$19)*12 -> 23241.775 | F25: ='40_Liquidity_Inputs'!$B$19+(F19-$C$19)*12 -> 25407.56
A26: Max allowable net debt | B26: PHP mn | C26: =C25*'40_Liquidity_Inputs'!$B$20 -> 81000 | D26: =D25*'40_Liquidity_Inputs'!$B$20 -> 74873.339 | E26: =E25*'40_Liquidity_Inputs'!$B$20 -> 104587.99 | F26: =F25*'40_Liquidity_Inputs'!$B$20 -> 114334.02
A27: Covenant Headroom | B27: PHP mn | C27: =C26-'40_Liquidity_Inputs'!$B$18 -> 41000 | D27: =D26-'40_Liquidity_Inputs'!$B$18 -> 34873.339 | E27: =E26-'40_Liquidity_Inputs'!$B$18 -> 64587.985 | F27: =F26-'40_Liquidity_Inputs'!$B$18 -> 74334.018 | G27: Max allowable net debt - actual net debt
A28: Minimum cash buffer | B28: PHP mn | C28: ='40_Liquidity_Inputs'!$B$16 -> 2000 | D28: ='40_Liquidity_Inputs'!$B$16 -> 2000 | E28: ='40_Liquidity_Inputs'!$B$16 -> 2000 | F28: ='40_Liquidity_Inputs'!$B$16 -> 2000
A29: Buffer headroom | B29: PHP mn | C29: =C24-C28 -> 22297.322 | D29: =D24-D28 -> 21606.348 | E29: =E24-E28 -> 21185.98 | F29: =F24-F28 -> 16214.824
A30: Liquidity runway | B30: days | C30: =IF((C20+'40_Liquidity_Inputs'!$B$17+C34+C36)>0,IF(C24>C28,((C24-C28)/(C20+'40_Liquidity_Inputs'!$B$17+C34+C36))*30,0),999) -> 2229.7322 | D30: =IF((D20+'40_Liquidity_Inputs'!$B$17+D34+D36)>0,IF(D24>D28,((D24-D28)/(D20+'40_Liquidity_Inputs'!$B$17+D34+D36))*30,0),999) -> 1454.4935 | E30: =IF((E20+'40_Liquidity_Inputs'!$B$17+E34+E36)>0,IF(E24>E28,((E24-E28)/(E20+'40_Liquidity_Inputs'!$B$17+E34+E36))*30,0),999) -> 4627.8672 | F30: =IF((F20+'40_Liquidity_Inputs'!$B$17+F34+F36)>0,IF(F24>F28,((F24-F28)/(F20+'40_Liquidity_Inputs'!$B$17+F34+F36))*30,0),999) -> 611.07175 | G30: Days to min cash buffer after one-time stress draw and monthly regulatory recovery drag
A31: Incremental gen cost subject to recovery | B31: PHP mn/month | C31: =MAX(C9-$C$9,0) -> 0 | D31: =MAX(D9-$C$9,0) -> 292.63789 | E31: =MAX(E9-$C$9,0) -> 1015.3777 | F31: =MAX(F9-$C$9,0) -> 2530.3372 | G31: Monthly shock increment vs base total fuel spend (proxy for pass-through eligible generation cost)
A32: Immediate recovery ratio | B32: % | C32: ='40_Liquidity_Inputs'!B25 -> 1 | D32: ='40_Liquidity_Inputs'!C25 -> 0.9 | E32: ='40_Liquidity_Inputs'!D25 -> 0.75 | F32: ='40_Liquidity_Inputs'!E25 -> 0.6 | G32: Linked regulatory recovery assumption
A33: Monthly billed gen charge adj. | B33: PHP mn/month | C33: =C31*C32 -> 0 | D33: =D31*D32 -> 263.3741 | E33: =E31*E32 -> 761.53327 | F33: =F31*F32 -> 1518.2023 | G33: Monthly billed generation charge adjustment
A34: Monthly deferred amount | B34: PHP mn/month | C34: =C31*(1-C32) -> 0 | D34: =D31*(1-D32) -> 29.263789 | E34: =E31*(1-E32) -> 253.84442 | F34: =F31*(1-F32) -> 1012.1349 | G34: Unrecovered portion deferred into regulatory receivable
A35: Disallowance pct | B35: % | C35: ='40_Liquidity_Inputs'!B26 -> 0.005 | D35: ='40_Liquidity_Inputs'!C26 -> 0.01 | E35: ='40_Liquidity_Inputs'!D26 -> 0.02 | F35: ='40_Liquidity_Inputs'!E26 -> 0.04 | G35: Linked refund / disallowance assumption
A36: Monthly refund provision | B36: PHP mn/month | C36: =C31*C35 -> 0 | D36: =D31*D35 -> 2.9263789 | E36: =E31*E35 -> 20.307554 | F36: =F31*F35 -> 101.21349 | G36: Potential refund / clawback after verification
A37: Collection months within horizon | B37: months | C37: =MAX(0,C21-ROUNDUP('40_Liquidity_Inputs'!B27/30,0)) -> 0 | D37: =MAX(0,D21-ROUNDUP('40_Liquidity_Inputs'!C27/30,0)) -> 0 | E37: =MAX(0,E21-ROUNDUP('40_Liquidity_Inputs'!D27/30,0)) -> 2 | F37: =MAX(0,F21-ROUNDUP('40_Liquidity_Inputs'!E27/30,0)) -> 5 | G37: Monthly bills collected after customer lag
A38: Cash collected within horizon | B38: PHP mn | C38: =C33*C37 -> 0 | D38: =D33*D37 -> 0 | E38: =E33*E37 -> 1523.0665 | F38: =F33*F37 -> 7591.0115 | G38: Informational timing output; not directly added to base liquidity model
A39: True-up horizon | B39: months | C39: ='40_Liquidity_Inputs'!B29 -> 36 | D39: ='40_Liquidity_Inputs'!C29 -> 36 | E39: ='40_Liquidity_Inputs'!D29 -> 36 | F39: ='40_Liquidity_Inputs'!E29 -> 36 | G39: Linked true-up horizon
A40: Carrying cost p.a. | B40: % | C40: ='40_Liquidity_Inputs'!B30 -> 0.07 | D40: ='40_Liquidity_Inputs'!C30 -> 0.07 | E40: ='40_Liquidity_Inputs'!D30 -> 0.07 | F40: ='40_Liquidity_Inputs'!E30 -> 0.07 | G40: Linked carrying cost
A41: Roll-forward multiplier | B41: x | C41: =1-1/C39+C40/12 -> 0.97805556 | D41: =1-1/D39+D40/12 -> 0.97805556 | E41: =1-1/E39+E40/12 -> 0.97805556 | F41: =1-1/F39+F40/12 -> 0.97805556 | G41: Monthly regulatory asset roll-forward factor
A42: Regulatory receivable balance | B42: PHP mn | C42: =IF(C21=0,0,IF(ABS(C41-1)<0.000001,C34*C21,C34*((C41^C21)-1)/(C41-1))) -> 0 | D42: =IF(D21=0,0,IF(ABS(D41-1)<0.000001,D34*D21,D34*((D41^D21)-1)/(D41-1))) -> 29.263789 | E42: =IF(E21=0,0,IF(ABS(E41-1)<0.000001,E34*E21,E34*((E41^E21)-1)/(E41-1))) -> 744.94408 | F42: =IF(F21=0,0,IF(ABS(F41-1)<0.000001,F34*F21,F34*((F41^F21)-1)/(F41-1))) -> 5749.2372 | G42: Closed-form balance for repeated monthly deferrals over the horizon
A43: Refund provision cumulative | B43: PHP mn | C43: =C36*MAX(0,C21-'40_Liquidity_Inputs'!B28) -> 0 | D43: =D36*MAX(0,D21-'40_Liquidity_Inputs'!C28) -> 0 | E43: =E36*MAX(0,E21-'40_Liquidity_Inputs'!D28) -> 40.615108 | F43: =F36*MAX(0,F21-'40_Liquidity_Inputs'!E28) -> 506.06744 | G43: Cumulative refund cash-out within the horizon

Sheet 50_Triggers_Playbook
A1: Module 4 — Trigger Matrix and Operating Playbook
A2: Current levels and duration counters are editable monitoring inputs. The status field updates automatically and links market conditions to actions.
A5: Trigger | B5: Operator | C5: Current level | D5: Threshold | E5: Unit | F5: Duration actual | G5: Duration threshold | H5: Status | I5: Action
A6: Brent | B6: > | C6: 93.04 | D6: 110 | E6: USD/bbl | F6: 5 | G6: 3 | H6: =IF(AND(IF(B6=">",C6>D6,C6<D6),F6>=G6),"TRIGGERED","Monitor") -> Monitor | I6: Activate hedging review / revise procurement cover
A7: JKM | B7: > | C7: 15.71 | D7: 20 | E7: USD/MMBtu | F7: 6 | G7: 5 | H7: =IF(AND(IF(B7=">",C7>D7,C7<D7),F7>=G7),"TRIGGERED","Monitor") -> Monitor | I7: Review gas dispatch / emergency LNG sourcing
A8: USD/PHP | B8: > | C8: 59.05 | D8: 58 | E8: PHP/USD | F8: 4 | G8: 3 | H8: =IF(AND(IF(B8=">",C8>D8,C8<D8),F8>=G8),"TRIGGERED","Monitor") -> TRIGGERED | I8: Reassess FX hedging / collateral plan
A9: WESM | B9: > | C9: 9500 | D9: 9000 | E9: PHP/MWh | F9: 3 | G9: 2 | H9: =IF(AND(IF(B9=">",C9>D9,C9<D9),F9>=G9),"TRIGGERED","Monitor") -> TRIGGERED | I9: Retail repricing review / reserve bidding posture
A10: Gas availability | B10: < | C10: 0.75 | D10: 0.8 | E10: % | F10: 7 | G10: 5 | H10: =IF(AND(IF(B10=">",C10>D10,C10<D10),F10>=G10),"TRIGGERED","Monitor") -> TRIGGERED | I10: Activate alternate dispatch / oil backup plan
A11: Coal delay | B11: > | C11: 10 | D11: 7 | E11: days | F11: 4 | G11: 2 | H11: =IF(AND(IF(B11=">",C11>D11,C11<D11),F11>=G11),"TRIGGERED","Monitor") -> TRIGGERED | I11: Increase inventory buffer / alternate logistics

Sheet 60_Outputs
A1: Deck-ready Outputs (matches RFP sample structures)
A2: This sheet is designed to be copied directly into the proposal or final board deck. It mirrors the sample structures shown in the RFP (pages 5–6).
A5: Scenario Matrix
A6: Variable | B6: Unit | C6: Base | D6: Scenario 1 | E6: Scenario 2 | F6: Scenario 3 | G6: Notes
A7: Duration_days | B7: days | C7: ='03_Scenarios'!C7 -> 0 | D7: ='03_Scenarios'!D7 -> 30 | E7: ='03_Scenarios'!E7 -> 120 | F7: ='03_Scenarios'!F7 -> 180 | G7: Linked to Module 1 scenario inputs
A8: Brent_USD_bbl | B8: USD/bbl | C8: ='03_Scenarios'!C8 -> 72.48 | D8: ='03_Scenarios'!D8 -> 80 | E8: ='03_Scenarios'!E8 -> 95 | F8: ='03_Scenarios'!F8 -> 135 | G8: Linked to Module 1 scenario inputs
A9: JKM_USD_MMBtu | B9: USD/MMBtu | C9: ='03_Scenarios'!C9 -> 10.725 | D9: ='03_Scenarios'!D9 -> 12.33375 | E9: ='03_Scenarios'!E9 -> 15.55125 | F9: ='03_Scenarios'!F9 -> 23.05875 | G9: Linked to Module 1 scenario inputs
A10: Newcastle_USD_t | B10: USD/t | C10: ='03_Scenarios'!C10 -> 115.8 | D10: ='03_Scenarios'!D10 -> 124.485 | E10: ='03_Scenarios'!E10 -> 141.855 | F10: ='03_Scenarios'!F10 -> 167.91 | G10: Linked to Module 1 scenario inputs
A11: FX_PHP_USD | B11: PHP/USD | C11: ='03_Scenarios'!C14 -> 57.741 | D11: ='03_Scenarios'!D14 -> 58.896 | E11: ='03_Scenarios'!E14 -> 60.34 | F11: ='03_Scenarios'!F14 -> 62.36 | G11: Linked to Module 1 scenario inputs
A12: CoalFreight_USD_t | B12: USD/t | C12: ='03_Scenarios'!C11 -> 10 | D12: ='03_Scenarios'!D11 -> 11.5 | E12: ='03_Scenarios'!E11 -> 14.5 | F12: ='03_Scenarios'!F11 -> 19.5 | G12: Linked to Module 1 scenario inputs
A13: LNG_Basis_Batangas_USD_MMBtu | B13: USD/MMBtu | C13: ='03_Scenarios'!C15 -> 0 | D13: ='03_Scenarios'!D15 -> 0.5 | E13: ='03_Scenarios'!E15 -> 2 | F13: ='03_Scenarios'!F15 -> 5 | G13: Linked DES basis vs JKM; see 10_FuelLanding for full basis + regas + delay split
A14: LNG_Availability_pct | B14: % | C14: ='03_Scenarios'!C16 -> 1 | D14: ='03_Scenarios'!D16 -> 0.97 | E14: ='03_Scenarios'!E16 -> 0.85 | F14: ='03_Scenarios'!F16 -> 0.7 | G14: Linked LNG throughput / availability multiplier used in WESM + reserve
A15: CoalDelay_days | B15: days | C15: ='03_Scenarios'!C17 -> 0 | D15: ='03_Scenarios'!D17 -> 5 | E15: ='03_Scenarios'!E17 -> 14 | F15: ='03_Scenarios'!F17 -> 28 | G15: Linked to Module 1 scenario inputs
A18: Generation Sensitivity Table
A19: Metric | B19: Unit | C19: Base | D19: Scenario 1 | E19: Scenario 2 | F19: Scenario 3 | G19: Source
A20: Coal SRMC | B20: PHP/MWh | C20: ='12_PlantSRMC'!C12 -> 3445.0582 | D20: ='12_PlantSRMC'!D12 -> 3790.0463 | E20: ='12_PlantSRMC'!E12 -> 4452.9419 | F20: ='12_PlantSRMC'!F12 -> 5527.6237 | G20: 12_PlantSRMC!row 12
A21: Gas SRMC | B21: PHP/MWh | C21: ='12_PlantSRMC'!C21 -> 4760.7253 | D21: ='12_PlantSRMC'!D21 -> 5740.1013 | E21: ='12_PlantSRMC'!E21 -> 7983.6926 | F21: ='12_PlantSRMC'!F21 -> 13014.425 | G21: 12_PlantSRMC!row 21
A22: Oil SRMC | B22: PHP/MWh | C22: ='12_PlantSRMC'!C28 -> 9892.8437 | D22: ='12_PlantSRMC'!D28 -> 10959.89 | E22: ='12_PlantSRMC'!E28 -> 13012.164 | F22: ='12_PlantSRMC'!F28 -> 18378.5 | G22: 12_PlantSRMC!row 28
A23: WESM Avg Luzon | B23: PHP/MWh | C23: ='13_MeritOrder_WESM'!C16 -> 4538.2781 | D23: ='13_MeritOrder_WESM'!D16 -> 5446.3888 | E23: ='13_MeritOrder_WESM'!E16 -> 8870.2828 | F23: ='13_MeritOrder_WESM'!F16 -> 13638.82 | G23: 13_MeritOrder_WESM!row 16
A24: Reserve Price | B24: PHP/MW-h | C24: ='14_ReservePricing'!C7 -> 1134.5695 | D24: ='14_ReservePricing'!D7 -> 1524.9889 | E24: ='14_ReservePricing'!E7 -> 3104.599 | F24: ='14_ReservePricing'!F7 -> 6137.469 | G24: 14_ReservePricing!row 7
A25: Generation Gross Margin | B25: PHP mn/month | C25: ='15_GenMargin'!C20 -> 712.82494 | D25: ='15_GenMargin'!D20 -> 1067.9776 | E25: ='15_GenMargin'!E20 -> 3239.0297 | F25: ='15_GenMargin'!F20 -> 5691.1071 | G25: 15_GenMargin!row 20
A29: Supply & Retail Margin Sensitivity
A30: Portfolio Segment | B30: Unit | C30: Base | D30: Scenario 1 | E30: Scenario 2 | F30: Scenario 3 | G30: Source
A31: BCQ Exposure | B31: PHP mn/month | C31: ='21_SupplyWholesale_Margin'!C7 -> 378.51658 | D31: ='21_SupplyWholesale_Margin'!D7 -> 106.08336 | E31: ='21_SupplyWholesale_Margin'!E7 -> -921.08485 | F31: ='21_SupplyWholesale_Margin'!F7 -> -2351.646 | G31: 21_SupplyWholesale_Margin!row 7
A32: Spot Sales | B32: PHP mn/month | C32: ='21_SupplyWholesale_Margin'!C8 -> 82.012059 | D32: ='21_SupplyWholesale_Margin'!D8 -> 123.96603 | E32: ='21_SupplyWholesale_Margin'!E8 -> 385.47497 | F32: ='21_SupplyWholesale_Margin'!F8 -> 673.02921 | G32: 21_SupplyWholesale_Margin!row 8
A33: Retail Fixed | B33: PHP mn/month | C33: ='31_Retail_EBIT'!C6 -> 612.43049 | D33: ='31_Retail_EBIT'!D6 -> 424.78726 | E33: ='31_Retail_EBIT'!E6 -> -252.43653 | F33: ='31_Retail_EBIT'!F6 -> -1147.9537 | G33: 31_Retail_EBIT!row 6
A34: Portfolio EBIT | B34: PHP mn/month | C34: ='31_Retail_EBIT'!C9 -> 1259.5229 | D34: ='31_Retail_EBIT'!D9 -> 966.90613 | E34: ='31_Retail_EBIT'!E9 -> -93.649037 | F34: ='31_Retail_EBIT'!F9 -> -1508.3497 | G34: 31_Retail_EBIT!row 9
A35: Supply & Wholesale Margin | B35: PHP mn/month | C35: ='21_SupplyWholesale_Margin'!C12 -> 451.3803 | D35: ='21_SupplyWholesale_Margin'!D12 -> 275.38769 | E35: ='21_SupplyWholesale_Margin'!E12 -> -284.83794 | F35: ='21_SupplyWholesale_Margin'!F12 -> -1141.7326 | G35: 21_SupplyWholesale_Margin!row 12
A39: Liquidity Stress Structure
A40: Metric | B40: Unit | C40: Base | D40: 30 Days | E40: 90 Days | F40: 180 Days | G40: Source
A41: Working Capital | B41: PHP mn | C41: ='41_Liquidity_Model'!C16 -> 418.35567 | D41: ='41_Liquidity_Model'!D16 -> 522.36973 | E41: ='41_Liquidity_Model'!E16 -> 707.80841 | F41: ='41_Liquidity_Model'!F16 -> 1050.4696 | G41: 41_Liquidity_Model!row 16
A42: LC Requirements | B42: PHP mn | C42: ='41_Liquidity_Model'!C18 -> 284.32195 | D42: ='41_Liquidity_Model'!D18 -> 428.56191 | E42: ='41_Liquidity_Model'!E18 -> 731.09623 | F42: ='41_Liquidity_Model'!F18 -> 1383.1814 | G42: 41_Liquidity_Model!row 18
A43: Cash Balance | B43: PHP mn | C43: ='41_Liquidity_Model'!C24 -> 24297.322 | D43: ='41_Liquidity_Model'!D24 -> 23606.348 | E43: ='41_Liquidity_Model'!E24 -> 23185.98 | F43: ='41_Liquidity_Model'!F24 -> 18214.824 | G43: 41_Liquidity_Model!row 24
A44: Covenant Headroom | B44: PHP mn | C44: ='41_Liquidity_Model'!C27 -> 41000 | D44: ='41_Liquidity_Model'!D27 -> 34873.339 | E44: ='41_Liquidity_Model'!E27 -> 64587.985 | F44: ='41_Liquidity_Model'!F27 -> 74334.018 | G44: 41_Liquidity_Model!row 27
A45: Liquidity Runway | B45: days | C45: ='41_Liquidity_Model'!C30 -> 2229.7322 | D45: ='41_Liquidity_Model'!D30 -> 1454.4935 | E45: ='41_Liquidity_Model'!E30 -> 4627.8672 | F45: ='41_Liquidity_Model'!F30 -> 611.07175 | G45: 41_Liquidity_Model!row 30
A46: Regulatory receivable balance | B46: PHP mn | C46: ='41_Liquidity_Model'!C42 -> 0 | D46: ='41_Liquidity_Model'!D42 -> 29.263789 | E46: ='41_Liquidity_Model'!E42 -> 744.94408 | F46: ='41_Liquidity_Model'!F42 -> 5749.2372 | G46: 41_Liquidity_Model!row 42
A47: Immediate recovery ratio | B47: % | C47: ='41_Liquidity_Model'!C32 -> 1 | D47: ='41_Liquidity_Model'!D32 -> 0.9 | E47: ='41_Liquidity_Model'!E32 -> 0.75 | F47: ='41_Liquidity_Model'!F32 -> 0.6 | G47: 41_Liquidity_Model!row 32
A48: Refund provision | B48: PHP mn | C48: ='41_Liquidity_Model'!C43 -> 0 | D48: ='41_Liquidity_Model'!D43 -> 0 | E48: ='41_Liquidity_Model'!E43 -> 40.615108 | F48: ='41_Liquidity_Model'!F43 -> 506.06744 | G48: 41_Liquidity_Model!row 43
A49: Trigger Matrix Summary
A50: Trigger | B50: Current | C50: Threshold | D50: Status | E50: Action | F50: Duration actual | G50: Duration threshold
A51: ='50_Triggers_Playbook'!A6 -> Brent | B51: ='50_Triggers_Playbook'!C6 -> 93.04 | C51: ='50_Triggers_Playbook'!D6 -> 110 | D51: ='50_Triggers_Playbook'!H6 -> Monitor | E51: ='50_Triggers_Playbook'!I6 -> Activate hedging review / revise procurement cover | F51: ='50_Triggers_Playbook'!F6 -> 5 | G51: ='50_Triggers_Playbook'!G6 -> 3
A52: ='50_Triggers_Playbook'!A7 -> JKM | B52: ='50_Triggers_Playbook'!C7 -> 15.71 | C52: ='50_Triggers_Playbook'!D7 -> 20 | D52: ='50_Triggers_Playbook'!H7 -> Monitor | E52: ='50_Triggers_Playbook'!I7 -> Review gas dispatch / emergency LNG sourcing | F52: ='50_Triggers_Playbook'!F7 -> 6 | G52: ='50_Triggers_Playbook'!G7 -> 5
A53: ='50_Triggers_Playbook'!A8 -> USD/PHP | B53: ='50_Triggers_Playbook'!C8 -> 59.05 | C53: ='50_Triggers_Playbook'!D8 -> 58 | D53: ='50_Triggers_Playbook'!H8 -> TRIGGERED | E53: ='50_Triggers_Playbook'!I8 -> Reassess FX hedging / collateral plan | F53: ='50_Triggers_Playbook'!F8 -> 4 | G53: ='50_Triggers_Playbook'!G8 -> 3
A54: ='50_Triggers_Playbook'!A9 -> WESM | B54: ='50_Triggers_Playbook'!C9 -> 9500 | C54: ='50_Triggers_Playbook'!D9 -> 9000 | D54: ='50_Triggers_Playbook'!H9 -> TRIGGERED | E54: ='50_Triggers_Playbook'!I9 -> Retail repricing review / reserve bidding posture | F54: ='50_Triggers_Playbook'!F9 -> 3 | G54: ='50_Triggers_Playbook'!G9 -> 2
A55: ='50_Triggers_Playbook'!A10 -> Gas availability | B55: ='50_Triggers_Playbook'!C10 -> 0.75 | C55: ='50_Triggers_Playbook'!D10 -> 0.8 | D55: ='50_Triggers_Playbook'!H10 -> TRIGGERED | E55: ='50_Triggers_Playbook'!I10 -> Activate alternate dispatch / oil backup plan | F55: ='50_Triggers_Playbook'!F10 -> 7 | G55: ='50_Triggers_Playbook'!G10 -> 5
A56: ='50_Triggers_Playbook'!A11 -> Coal delay | B56: ='50_Triggers_Playbook'!C11 -> 10 | C56: ='50_Triggers_Playbook'!D11 -> 7 | D56: ='50_Triggers_Playbook'!H11 -> TRIGGERED | E56: ='50_Triggers_Playbook'!I11 -> Increase inventory buffer / alternate logistics | F56: ='50_Triggers_Playbook'!F11 -> 4 | G56: ='50_Triggers_Playbook'!G11 -> 2

Sheet 99_Checks
A1: Model Checks and Tie-outs
A2: The checks below are intentionally simple and transparent. They are designed to flag missing inputs, sign errors, merit-order inconsistencies, bridge tie-out issues, and liquidity pressure.
A5: Check | B5: Status | C5: Value / Note | D5: Threshold | E5: Comment
A6: Scenario inputs complete | B6: =IF(COUNTA('03_Scenarios'!C7:F20)=56,"OK","FLAG") -> OK | C6: =COUNTA('03_Scenarios'!C7:F20) -> 56 | D6: 56 filled cells | E6: All scenario input cells populated
A7: Coal SRMC positive in all scenarios | B7: =IF(AND('12_PlantSRMC'!C12>0,'12_PlantSRMC'!D12>0,'12_PlantSRMC'!E12>0,'12_PlantSRMC'!F12>0),"OK","FLAG") -> OK | C7: =MIN('12_PlantSRMC'!C12:F12) -> 3445.0582 | D7: >0 | E7: No negative SRMCs
A8: Gas availability bounded 0-100% | B8: =IF(AND('03_Scenarios'!C16>=0,'03_Scenarios'!C16<=1,'03_Scenarios'!D16>=0,'03_Scenarios'!D16<=1,'03_Scenarios'!E16>=0,'03_Scenarios'!E16<=1,'03_Scenarios'!F16>=0,'03_Scenarios'!F16<=1),"OK","FLAG") -> OK | C8: ="See scenario inputs" -> See scenario inputs | D8: 0% to 100% | E8: Availability multipliers valid
A9: Merit order monotonic in all scenarios | B9: =IF(AND('13_MeritOrder_WESM'!C19="OK",'13_MeritOrder_WESM'!D19="OK",'13_MeritOrder_WESM'!E19="OK",'13_MeritOrder_WESM'!F19="OK"),"OK","FLAG") -> OK | C9: ="See 13_MeritOrder_WESM" -> See 13_MeritOrder_WESM | D9: OK | E9: Coal <= Gas <= Oil SRMC
A10: Supply bridge ties — S1 | B10: =IF(AND('22_MarginBridge'!B13<0.01,'22_MarginBridge'!B13>-0.01),"OK","FLAG") -> OK | C10: ='22_MarginBridge'!B13 -> 0 | D10: +/-0.01 | E10: Scenario 1 bridge reconciliation
A11: Supply bridge ties — S2 | B11: =IF(AND('22_MarginBridge'!C13<0.01,'22_MarginBridge'!C13>-0.01),"OK","FLAG") -> OK | C11: ='22_MarginBridge'!C13 -> 0 | D11: +/-0.01 | E11: Scenario 2 bridge reconciliation
A12: Supply bridge ties — S3 | B12: =IF(AND('22_MarginBridge'!D13<0.01,'22_MarginBridge'!D13>-0.01),"OK","FLAG") -> OK | C12: ='22_MarginBridge'!D13 -> 0 | D12: +/-0.01 | E12: Scenario 3 bridge reconciliation
A13: Retail EBIT summary ties | B13: =IF(AND(('31_Retail_EBIT'!C9-SUM('31_Retail_EBIT'!C6:C8))<0.01,('31_Retail_EBIT'!C9-SUM('31_Retail_EBIT'!C6:C8))>-0.01),"OK","FLAG") -> OK | C13: ='31_Retail_EBIT'!C9-SUM('31_Retail_EBIT'!C6:C8) -> 0 | D13: +/-0.01 | E13: Base portfolio EBIT equals segment sum
A14: Base cash balance above minimum buffer | B14: =IF('41_Liquidity_Model'!C24>='41_Liquidity_Model'!C28,"OK","FLAG") -> OK | C14: ='41_Liquidity_Model'!C24-'41_Liquidity_Model'!C28 -> 22297.322 | D14: >=0 | E14: Base liquidity above board buffer
A15: Outputs WESM link check | B15: =IF(AND('60_Outputs'!C23='13_MeritOrder_WESM'!C16,'60_Outputs'!D23='13_MeritOrder_WESM'!D16,'60_Outputs'!E23='13_MeritOrder_WESM'!E16,'60_Outputs'!F23='13_MeritOrder_WESM'!F16),"OK","FLAG") -> OK | C15: =SUM(ABS('60_Outputs'!C23-'13_MeritOrder_WESM'!C16),ABS('60_Outputs'!D23-'13_MeritOrder_WESM'!D16),ABS('60_Outputs'!E23-'13_MeritOrder_WESM'!E16),ABS('60_Outputs'!F23-'13_MeritOrder_WESM'!F16)) -> 0 | D15: 0 | E15: Deck-ready WESM output must tie exactly to merit-order sheet
A16: Overall model status | B16: =IF(AND(COUNTIF(B6:B39,"FLAG")=0,C46=0),"MODEL OK","REVIEW") -> MODEL OK | C16: =COUNTIF(B6:B33,"FLAG") | D16: 0 flags target | E16: If any FLAG remains, review assumptions or formulas.
A18: Change log — workbook updates made for realism / traceability
A19: 01_Constants | B19: Added GAR-to-CV conversion factor and GAR 5000 / 5250 / 5500 CV cases with comments.
A20: 03_Scenarios | B20: Repurposed LNG ship+regas input into DES basis and renamed gas throughput to LNG_Availability_pct.
A21: 10_FuelLanding | B21: Coal now normalized on a GJ basis; LNG now split into JKM + DES basis + regas + delay/demurrage.
A22: 11_Plants | B22: Added coal GAR selector / CV lookup; updated HELE coal heat rate default and gas heat-rate comments.
A23: 12_PlantSRMC | B23: Coal SRMC now uses PHP/GJ landed cost normalization; gas SRMC linked to DES LNG landed cost build-up.
A24: 40_Liquidity_Inputs | B24: Added AGRA-style recovery / disallowance / true-up / carrying-cost input block; refined gas/oil payables placeholders to avoid unrealistic negative working-capital outputs.
A25: 41_Liquidity_Model | B25: Added monthly regulatory recovery engine and linked it into cash balance / runway outputs.
A26: 60_Outputs | B26: Added regulatory receivable balance, immediate recovery ratio, and refund provision to liquidity outputs.
A27: 13/14_MeritOrder_WESM | B27: Retained realistic Luzon stack; LNG_Availability_pct continues to drive gas capacity and reserve scarcity.
A28: 99_Checks | B28: Added propagation checks for coal CV, LNG landed cost link, AGRA output link, and S3 oil marginality.
A29: 02_Inputs_Base | B29: Added renewable block-shape inputs, hydro energy-budget proxy, and SPC sensitivity toggle with source comments.
A30: 13_MeritOrder_WESM | B30: Recalibrated solar/wind profiles via 02_Inputs_Base links, added hydro energy-budget scaling and optional SPC capping logic.
A31: AGRA output link check | B31: =IF(AND('60_Outputs'!C46='41_Liquidity_Model'!C42,'60_Outputs'!D46='41_Liquidity_Model'!D42,'60_Outputs'!E46='41_Liquidity_Model'!E42,'60_Outputs'!F46='41_Liquidity_Model'!F42,'60_Outputs'!C47='41_Liquidity_Model'!C32,'60_Outputs'!F48='41_Liquidity_Model'!F43),"OK","FLAG") -> OK | C31: =SUM(ABS('60_Outputs'!C46-'41_Liquidity_Model'!C42),ABS('60_Outputs'!D46-'41_Liquidity_Model'!D42),ABS('60_Outputs'!E46-'41_Liquidity_Model'!E42),ABS('60_Outputs'!F46-'41_Liquidity_Model'!F42)) -> 0 | D31: 0 | E31: Deck-ready AGRA outputs must tie exactly to liquidity engine
A32: Coal CV and LNG landed-cost propagation | B32: =IF(AND(ABS('10_FuelLanding'!C13-'11_Plants'!F5)<0.0001,ABS('12_PlantSRMC'!C18-'10_FuelLanding'!C21)<0.0001,ABS('12_PlantSRMC'!F18-'10_FuelLanding'!F21)<0.0001),"OK","FLAG") -> OK | C32: =SUM(ABS('10_FuelLanding'!C13-'11_Plants'!F5),ABS('12_PlantSRMC'!C18-'10_FuelLanding'!C21),ABS('12_PlantSRMC'!F18-'10_FuelLanding'!F21)) -> 0 | D32: <0.0001 | E32: GAR-selected coal CV and DES LNG landed-cost links must propagate end-to-end
A33: Scenario 3 peak marginal cluster = Oil | B33: =IF('13_MeritOrder_WESM'!F11="Oil","OK","FLAG") -> OK | C33: ='13_MeritOrder_WESM'!F11 -> Oil | D33: Oil | E33: Confirms severe disruption can push peak Luzon marginal setter to oil
A34: Solar selected-season CF anchor | B34: =IF(AND(ABS('02_Inputs_Base'!$L$24-0.16)<=0.01,'02_Inputs_Base'!$L$24>0),"OK","FLAG") -> OK | C34: ='02_Inputs_Base'!$L$24 -> 0.1615 | D34: 16% +/-1% | E34: Selected-season implied solar CF should align to NGCP planning anchor
A35: Wind selected-season CF anchor | B35: =IF(AND(ABS('02_Inputs_Base'!$L$25-0.3)<=0.02,'02_Inputs_Base'!$L$25>0),"OK","FLAG") -> OK | C35: ='02_Inputs_Base'!$L$25 -> 0.29925 | D35: 30% +/-2% | E35: Selected-season implied wind CF should align to NGCP planning anchor
A36: Base LWAP within sanity band | B36: =IF(AND('60_Outputs'!C23>=3500,'60_Outputs'!C23<=5500),"OK","FLAG") -> OK | C36: ='60_Outputs'!C23 -> 4538.2781 | D36: 3,500 to 5,500 | E36: Base LWAP proxy sanity check
A37: SPC toggle logic not binding when off | B37: =IF('02_Inputs_Base'!$I$36=0,"OK",IF('60_Outputs'!F23<='02_Inputs_Base'!$I$37,"OK","FLAG")) -> OK | C37: ='02_Inputs_Base'!$I$36 -> 0 | D37: 0 or capped | E37: If SPC toggle is off, no cap applied; if on, outputs must not exceed cap
A38: Hydro budget scale valid | B38: =IF(AND('02_Inputs_Base'!$L$33>0,'02_Inputs_Base'!$L$33<=1),"OK","FLAG") -> OK | C38: ='02_Inputs_Base'!$L$33 -> 0.69083008 | D38: 0 to 1 | E38: Hydro energy-budget scaling factor should be bounded
A39: Outputs free of errors | B39: =IF(C46=0,"OK","FLAG") -> OK | C39: =C46 -> 0 | D39: 0 | E39: Key output ranges should have no #N/A / #DIV/0! / #REF! / #NAME? / #VALUE!
A41: Error audit (key ranges)
A42: Sheet | B42: Before | C42: After | D42: Status | E42: Comment
A43: 10_FuelLanding | B43: 2 | C43: =COUNTIF('10_FuelLanding'!A1:G28,"#N/A")+COUNTIF('10_FuelLanding'!A1:G28,"#DIV/0!")+COUNTIF('10_FuelLanding'!A1:G28,"#VALUE!")+COUNTIF('10_FuelLanding'!A1:G28,"#REF!")+COUNTIF('10_FuelLanding'!A1:G28,"#NAME?") -> 0 | D43: =IF(C43=0,"OK","FLAG") -> OK | E43: Original file had cached #N/A in audit-note cells plus unquoted cross-sheet formula issues
A44: 13_MeritOrder_WESM | B44: 0 | C44: =COUNTIF('13_MeritOrder_WESM'!A1:P71,"#N/A")+COUNTIF('13_MeritOrder_WESM'!A1:P71,"#DIV/0!")+COUNTIF('13_MeritOrder_WESM'!A1:P71,"#VALUE!")+COUNTIF('13_MeritOrder_WESM'!A1:P71,"#REF!")+COUNTIF('13_MeritOrder_WESM'!A1:P71,"#NAME?") -> 0 | D44: =IF(C44=0,"OK","FLAG") -> OK | E44: Merit-order range should be clean
A45: 60_Outputs | B45: 0 | C45: =COUNTIF('60_Outputs'!A1:G56,"#N/A")+COUNTIF('60_Outputs'!A1:G56,"#DIV/0!")+COUNTIF('60_Outputs'!A1:G56,"#VALUE!")+COUNTIF('60_Outputs'!A1:G56,"#REF!")+COUNTIF('60_Outputs'!A1:G56,"#NAME?") -> 0 | D45: =IF(C45=0,"OK","FLAG") -> OK | E45: Deck-ready outputs must contain no errors
A46: Total key-range errors | B46: 2 | C46: =C43+C44+C45+(COUNTIF(B6:E46,"#N/A")+COUNTIF(B6:E46,"#DIV/0!")+COUNTIF(B6:E46,"#VALUE!")+COUNTIF(B6:E46,"#REF!")+COUNTIF(B6:E46,"#NAME?")) -> 0 | D46: =IF(C46=0,"OK","FLAG") -> OK | E46: Overall key-range error count should be zero after repair
